# Comparing `tmp/pyc3dtools-0.1.2.win-amd64.zip` & `tmp/pyc3dtools-0.2.1.win-amd64.zip`

## zipinfo {}

```diff
@@ -1,17 +1,17 @@
-Zip file size: 8175 bytes, number of entries: 15
-drwxrwxrwx  2.0 fat        0 b- stor 23-May-05 20:38 Python311/
-drwxrwxrwx  2.0 fat        0 b- stor 23-May-05 20:38 Python311/Lib/
-drwxrwxrwx  2.0 fat        0 b- stor 23-May-05 20:38 Python311/Lib/site-packages/
-drwxrwxrwx  2.0 fat        0 b- stor 23-May-05 20:38 Python311/Lib/site-packages/pyc3dtools/
-drwxrwxrwx  2.0 fat        0 b- stor 23-May-05 20:38 Python311/Lib/site-packages/pyc3dtools-0.1.2-py3.11.egg-info/
-drwxrwxrwx  2.0 fat        0 b- stor 23-May-05 20:38 Python311/Lib/site-packages/pyc3dtools/__pycache__/
--rw-rw-rw-  2.0 fat     4138 b- defN 23-May-05 20:30 Python311/Lib/site-packages/pyc3dtools/pyc3dtools.py
--rw-rw-rw-  2.0 fat       41 b- defN 23-Apr-30 17:31 Python311/Lib/site-packages/pyc3dtools/__init__.py
--rw-rw-rw-  2.0 fat     6320 b- defN 23-May-05 20:38 Python311/Lib/site-packages/pyc3dtools/__pycache__/pyc3dtools.cpython-311.pyc
--rw-rw-rw-  2.0 fat      227 b- defN 23-May-05 20:38 Python311/Lib/site-packages/pyc3dtools/__pycache__/__init__.cpython-311.pyc
--rw-rw-rw-  2.0 fat        1 b- defN 23-May-05 20:38 Python311/Lib/site-packages/pyc3dtools-0.1.2-py3.11.egg-info/dependency_links.txt
--rw-rw-rw-  2.0 fat     3728 b- defN 23-May-05 20:38 Python311/Lib/site-packages/pyc3dtools-0.1.2-py3.11.egg-info/PKG-INFO
--rw-rw-rw-  2.0 fat       20 b- defN 23-May-05 20:38 Python311/Lib/site-packages/pyc3dtools-0.1.2-py3.11.egg-info/requires.txt
--rw-rw-rw-  2.0 fat      243 b- defN 23-May-05 20:38 Python311/Lib/site-packages/pyc3dtools-0.1.2-py3.11.egg-info/SOURCES.txt
--rw-rw-rw-  2.0 fat       11 b- defN 23-May-05 20:38 Python311/Lib/site-packages/pyc3dtools-0.1.2-py3.11.egg-info/top_level.txt
-15 files, 14729 bytes uncompressed, 5361 bytes compressed:  63.6%
+Zip file size: 10025 bytes, number of entries: 15
+drwxrwxrwx  2.0 fat        0 b- stor 23-May-08 19:22 Python311/
+drwxrwxrwx  2.0 fat        0 b- stor 23-May-08 19:22 Python311/Lib/
+drwxrwxrwx  2.0 fat        0 b- stor 23-May-08 19:22 Python311/Lib/site-packages/
+drwxrwxrwx  2.0 fat        0 b- stor 23-May-08 19:22 Python311/Lib/site-packages/pyc3dtools/
+drwxrwxrwx  2.0 fat        0 b- stor 23-May-08 19:22 Python311/Lib/site-packages/pyc3dtools-0.2.1-py3.11.egg-info/
+drwxrwxrwx  2.0 fat        0 b- stor 23-May-08 19:22 Python311/Lib/site-packages/pyc3dtools/__pycache__/
+-rw-rw-rw-  2.0 fat     5460 b- defN 23-May-08 19:01 Python311/Lib/site-packages/pyc3dtools/pyc3dtools.py
+-rw-rw-rw-  2.0 fat       88 b- defN 23-May-08 18:15 Python311/Lib/site-packages/pyc3dtools/__init__.py
+-rw-rw-rw-  2.0 fat     9280 b- defN 23-May-08 19:22 Python311/Lib/site-packages/pyc3dtools/__pycache__/pyc3dtools.cpython-311.pyc
+-rw-rw-rw-  2.0 fat      275 b- defN 23-May-08 19:22 Python311/Lib/site-packages/pyc3dtools/__pycache__/__init__.cpython-311.pyc
+-rw-rw-rw-  2.0 fat        1 b- defN 23-May-08 19:22 Python311/Lib/site-packages/pyc3dtools-0.2.1-py3.11.egg-info/dependency_links.txt
+-rw-rw-rw-  2.0 fat     6757 b- defN 23-May-08 19:22 Python311/Lib/site-packages/pyc3dtools-0.2.1-py3.11.egg-info/PKG-INFO
+-rw-rw-rw-  2.0 fat       20 b- defN 23-May-08 19:22 Python311/Lib/site-packages/pyc3dtools-0.2.1-py3.11.egg-info/requires.txt
+-rw-rw-rw-  2.0 fat      243 b- defN 23-May-08 19:22 Python311/Lib/site-packages/pyc3dtools-0.2.1-py3.11.egg-info/SOURCES.txt
+-rw-rw-rw-  2.0 fat       11 b- defN 23-May-08 19:22 Python311/Lib/site-packages/pyc3dtools-0.2.1-py3.11.egg-info/top_level.txt
+15 files, 22135 bytes uncompressed, 7211 bytes compressed:  67.4%
```

## zipnote {}

```diff
@@ -6,15 +6,15 @@
 
 Filename: Python311/Lib/site-packages/
 Comment: 
 
 Filename: Python311/Lib/site-packages/pyc3dtools/
 Comment: 
 
-Filename: Python311/Lib/site-packages/pyc3dtools-0.1.2-py3.11.egg-info/
+Filename: Python311/Lib/site-packages/pyc3dtools-0.2.1-py3.11.egg-info/
 Comment: 
 
 Filename: Python311/Lib/site-packages/pyc3dtools/__pycache__/
 Comment: 
 
 Filename: Python311/Lib/site-packages/pyc3dtools/pyc3dtools.py
 Comment: 
@@ -24,23 +24,23 @@
 
 Filename: Python311/Lib/site-packages/pyc3dtools/__pycache__/pyc3dtools.cpython-311.pyc
 Comment: 
 
 Filename: Python311/Lib/site-packages/pyc3dtools/__pycache__/__init__.cpython-311.pyc
 Comment: 
 
-Filename: Python311/Lib/site-packages/pyc3dtools-0.1.2-py3.11.egg-info/dependency_links.txt
+Filename: Python311/Lib/site-packages/pyc3dtools-0.2.1-py3.11.egg-info/dependency_links.txt
 Comment: 
 
-Filename: Python311/Lib/site-packages/pyc3dtools-0.1.2-py3.11.egg-info/PKG-INFO
+Filename: Python311/Lib/site-packages/pyc3dtools-0.2.1-py3.11.egg-info/PKG-INFO
 Comment: 
 
-Filename: Python311/Lib/site-packages/pyc3dtools-0.1.2-py3.11.egg-info/requires.txt
+Filename: Python311/Lib/site-packages/pyc3dtools-0.2.1-py3.11.egg-info/requires.txt
 Comment: 
 
-Filename: Python311/Lib/site-packages/pyc3dtools-0.1.2-py3.11.egg-info/SOURCES.txt
+Filename: Python311/Lib/site-packages/pyc3dtools-0.2.1-py3.11.egg-info/SOURCES.txt
 Comment: 
 
-Filename: Python311/Lib/site-packages/pyc3dtools-0.1.2-py3.11.egg-info/top_level.txt
+Filename: Python311/Lib/site-packages/pyc3dtools-0.2.1-py3.11.egg-info/top_level.txt
 Comment: 
 
 Zip file comment:
```

## Python311/Lib/site-packages/pyc3dtools/pyc3dtools.py

```diff
@@ -1,107 +1,148 @@
 import requests,json
 import numpy as np
 import os
 from tqdm import tqdm
 from tqdm.utils import CallbackIOWrapper
 
-#API URL
-API_URL = "https://c3dtools.com/API/readC3D"
-#API_URL = "http://localhost:5001/API/readC3D"
 
 def readC3D(Token,file_path): 
 
+    API_URL = "https://c3dtools.com/API/readC3D"
     data = {'api_key':Token}  
 
     #r = requests.post(url = API_URL, files=file, data = data)    
     file_size = os.stat(file_path).st_size
     with open(file_path, "rb") as f:
         with tqdm(total=file_size, unit="B", unit_scale=True, unit_divisor=1024) as t:
             wrapped_file = CallbackIOWrapper(t.update, f, "read")
-            resp = requests.post(url = API_URL, data= data, files={'upload_file': wrapped_file})
-
-
-    result = json.loads(resp.text) 
+            resp = requests.post(url = API_URL, data= data, files={'upload_file': wrapped_file})   
 
     try:
+        result = json.loads(resp.text) 
         if 'error_msg' in result:
             return({
-                'error' : result['error_msg']
+                'error' : result['error_msg'],
+                'Status' : 'Failed'
             })
     
         else:
-            GP =  result["GP"]
-            Point = result["Point"]
-            Real_marker_index = result["Real_marker_index"]
-            Analog = result["Analog"]
-            Header = result["Header"]
-            Forceplates = result["Forceplate_list"]
-            Real_Markers = np.array(Point)
-            Real_Markers = Real_Markers[:,Real_marker_index,:]
-            result["Markers"] = Real_Markers
-
-
-            # COP :: null to 0
-            Forceplates
-
-
-            # List of Markers Label
-            gp_point_lbl_i = [
-                index for index in range(len(GP))
-                if GP[index]['Group_Name'] == 'POINT'
-            ][0]    
-            gp_point_lbl_ii = [
-                index for index in range(len(GP[gp_point_lbl_i]['List_Parameters']))
-                if GP[gp_point_lbl_i]['List_Parameters'][index]['Param_Name'] == 'LABELS'
-            ][0] 
-            gp_point_unit_i = [
-                index for index in range(len(GP[gp_point_lbl_i]['List_Parameters']))
-                if GP[gp_point_lbl_i]['List_Parameters'][index]['Param_Name'] == 'UNITS'
-            ][0] 
-            gp_point_Yscreen_i = [
-                index for index in range(len(GP[gp_point_lbl_i]['List_Parameters']))
-                if GP[gp_point_lbl_i]['List_Parameters'][index]['Param_Name'] == 'Y_SCREEN'
-            ][0] 
-            gp_point_Xscreen_i = [
-                index for index in range(len(GP[gp_point_lbl_i]['List_Parameters']))
-                if GP[gp_point_lbl_i]['List_Parameters'][index]['Param_Name'] == 'X_SCREEN'
-            ][0] 
-            Markers_lbl = GP[gp_point_lbl_i]['List_Parameters'][gp_point_lbl_ii]['Param_data']
-            Markers_Units = GP[gp_point_lbl_i]['List_Parameters'][gp_point_unit_i]['Param_data'][0]
-            Markers_YSCREEN = GP[gp_point_lbl_i]['List_Parameters'][gp_point_Yscreen_i]['Param_data'][0]
-            Markers_XSCREEN = GP[gp_point_lbl_i]['List_Parameters'][gp_point_Xscreen_i]['Param_data'][0]
-
-            #List of Analog channel Label
-            gp_analog_lbl_i = [
-                index for index in range(len(GP))
-                if GP[index]['Group_Name'] == 'ANALOG'
-            ][0]    
-            gp_analog_lbl_ii = [
-                index for index in range(len(GP[gp_analog_lbl_i]['List_Parameters']))
-                if GP[gp_analog_lbl_i]['List_Parameters'][index]['Param_Name'] == 'LABELS'
-            ][0] 
-            Analog_lbl = GP[gp_analog_lbl_i]['List_Parameters'][gp_analog_lbl_ii]['Param_data']
-
-
-
-            ## SORRY :)
-            for f in Forceplates:
-                 f['Origin'] = f['orgin']            
-
-            return({
-                'GP' : GP,
-                'Markers' : Real_Markers,
-                'Points' : Point,
-                'Analog' : Analog,
-                'Header' : Header,
-                'ForcePlate' : Forceplates,
-                'Markers Label' : Markers_lbl,
-                'Analog Label' : Analog_lbl,
-                'Units' : Markers_Units,
-                'Coordinate system' : [Markers_XSCREEN ,Markers_YSCREEN]
-            })
-    except (KeyError):
+            return GenerateOutput(result)
+            
+            
+    except:
             return({
                 'error' : 'Failed'
             })
 
     
+def getTRCMot(Token,file_path,des_path):          
+    API_URL = "https://c3dtools.com/API/getOpenSimData"
+    data = {'api_key':Token}  
+    file_name = os.path.basename(file_path)
+    file_size = os.stat(file_path).st_size
+    with open(file_path, "rb") as f:
+        with tqdm(total=file_size, unit="B", unit_scale=True, unit_divisor=1024) as t:
+            wrapped_file = CallbackIOWrapper(t.update, f, "read")
+            resp=requests.post(url = API_URL, stream=True ,data= data, files={'upload_file': wrapped_file})
+
+    try:
+        result = json.loads(resp.text)
+
+        if 'error_msg' in result:
+            return({'error' : result['error_msg'] , 'Status' : 'Failed'  })
+        else:
+            #write to file\
+            if 'mot' in result:
+                motFile = open(des_path+'/'+file_name[:-3]+'mot','w')
+                motFile.writelines(result['mot']['h1'])
+                motFile.writelines(result['mot']['h2'])
+                for d in result['mot']['data']:
+                    motFile.writelines(d)
+                motFile.close()
+            
+            if 'trc' in result:
+                trcFile = open(des_path+'/'+file_name[:-3]+'trc','w')
+                trcFile.writelines(result['trc']['h1'])
+                trcFile.writelines(result['trc']['h2'])
+                trcFile.writelines(result['trc']['h3'])
+                trcFile.writelines(result['trc']['h4'])
+                trcFile.writelines(result['trc']['h5'])
+                for d in result['trc']['data']:
+                    trcFile.writelines(d)
+                trcFile.close()
+
+            return GenerateOutput(result['c3d'])
+      
+    except:
+        return({'Status' : 'Failed'  })
+
+            
+
+
+
+def GenerateOutput(result):
+    GP =  result["GP"]
+    Point = result["Point"]
+    Real_marker_index = result["Real_marker_index"]
+    Analog = result["Analog"]
+    Header = result["Header"]
+    Forceplates = result["Forceplate_list"]
+    Real_Markers = np.array(Point)
+    Real_Markers = Real_Markers[:,Real_marker_index,:]
+    result["Markers"] = Real_Markers
+
+    # List of Markers Label
+    gp_point_lbl_i = [
+        index for index in range(len(GP))
+        if GP[index]['Group_Name'] == 'POINT'
+    ][0]    
+    gp_point_lbl_ii = [
+        index for index in range(len(GP[gp_point_lbl_i]['List_Parameters']))
+        if GP[gp_point_lbl_i]['List_Parameters'][index]['Param_Name'] == 'LABELS'
+    ][0] 
+    gp_point_unit_i = [
+        index for index in range(len(GP[gp_point_lbl_i]['List_Parameters']))
+        if GP[gp_point_lbl_i]['List_Parameters'][index]['Param_Name'] == 'UNITS'
+    ][0] 
+    gp_point_Yscreen_i = [
+        index for index in range(len(GP[gp_point_lbl_i]['List_Parameters']))
+        if GP[gp_point_lbl_i]['List_Parameters'][index]['Param_Name'] == 'Y_SCREEN'
+    ][0] 
+    gp_point_Xscreen_i = [
+        index for index in range(len(GP[gp_point_lbl_i]['List_Parameters']))
+        if GP[gp_point_lbl_i]['List_Parameters'][index]['Param_Name'] == 'X_SCREEN'
+    ][0] 
+    Markers_lbl = GP[gp_point_lbl_i]['List_Parameters'][gp_point_lbl_ii]['Param_data']
+    Markers_Units = GP[gp_point_lbl_i]['List_Parameters'][gp_point_unit_i]['Param_data'][0]
+    Markers_YSCREEN = GP[gp_point_lbl_i]['List_Parameters'][gp_point_Yscreen_i]['Param_data'][0]
+    Markers_XSCREEN = GP[gp_point_lbl_i]['List_Parameters'][gp_point_Xscreen_i]['Param_data'][0]
+
+    #List of Analog channel Label
+    gp_analog_lbl_i = [
+        index for index in range(len(GP))
+        if GP[index]['Group_Name'] == 'ANALOG'
+    ][0]    
+    gp_analog_lbl_ii = [
+        index for index in range(len(GP[gp_analog_lbl_i]['List_Parameters']))
+        if GP[gp_analog_lbl_i]['List_Parameters'][index]['Param_Name'] == 'LABELS'
+    ][0] 
+    Analog_lbl = GP[gp_analog_lbl_i]['List_Parameters'][gp_analog_lbl_ii]['Param_data']
+
+
+    ## SORRY :)
+    for f in Forceplates:
+            f['Origin'] = f['orgin']            
+
+    return({
+        'Status' : 'Success',
+        'GP' : GP,
+        'Markers' : Real_Markers,
+        'Points' : Point,
+        'Analog' : Analog,
+        'Header' : Header,
+        'ForcePlate' : Forceplates,
+        'Markers Label' : Markers_lbl,
+        'Analog Label' : Analog_lbl,
+        'Units' : Markers_Units,
+        'Coordinate system' : [Markers_XSCREEN ,Markers_YSCREEN]
+    })
```

## Python311/Lib/site-packages/pyc3dtools/__init__.py

```diff
@@ -1 +1,2 @@
-from pyc3dtools.pyc3dtools import readC3D
+from pyc3dtools.pyc3dtools import readC3D
+from pyc3dtools.pyc3dtools import getTRCMot
```

## Python311/Lib/site-packages/pyc3dtools/__pycache__/pyc3dtools.cpython-311.pyc

### Python bytecode

```diff
@@ -1,19 +1,19 @@
 magic:    0xa70d0d0a
-moddate:  0x22365564 (Fri May  5 17:00:18 2023 UTC)
-files sz: 4138
+moddate:  0xc6155964 (Mon May  8 15:31:18 2023 UTC)
+files sz: 5460
 code
    argcount  : 0
    nlocals   : 0
    stacksize : 2
    flags     : 0
    code
       0x9700640064016c005a00640064016c015a01640064016c025a03640064
       016c045a04640064026c056d055a050100640064036c066d075a07010064
-      045a08640584005a0964015300
+      0484005a08640584005a09640684005a0a64015300
      0           0 RESUME                   0
    
      1           2 LOAD_CONST               0 (0)
                  4 LOAD_CONST               1 (None)
                  6 IMPORT_NAME              0 (requests)
                  8 STORE_NAME               0 (requests)
                 10 LOAD_CONST               0 (0)
@@ -41,594 +41,1045 @@
      5          46 LOAD_CONST               0 (0)
                 48 LOAD_CONST               3 (('CallbackIOWrapper',))
                 50 IMPORT_NAME              6 (tqdm.utils)
                 52 IMPORT_FROM              7 (CallbackIOWrapper)
                 54 STORE_NAME               7 (CallbackIOWrapper)
                 56 POP_TOP
    
-     8          58 LOAD_CONST               4 ('https://c3dtools.com/API/readC3D')
-                60 STORE_NAME               8 (API_URL)
+     8          58 LOAD_CONST               4 (<code object readC3D, file "\Python311\Lib\site-packages\pyc3dtools\pyc3dtools.py", line 8>)
+                60 MAKE_FUNCTION            0
+                62 STORE_NAME               8 (readC3D)
    
-    11          62 LOAD_CONST               5 (<code object readC3D, file "\Python311\Lib\site-packages\pyc3dtools\pyc3dtools.py", line 11>)
-                64 MAKE_FUNCTION            0
-                66 STORE_NAME               9 (readC3D)
-                68 LOAD_CONST               1 (None)
-                70 RETURN_VALUE
+    38          64 LOAD_CONST               5 (<code object getTRCMot, file "\Python311\Lib\site-packages\pyc3dtools\pyc3dtools.py", line 38>)
+                66 MAKE_FUNCTION            0
+                68 STORE_NAME               9 (getTRCMot)
+   
+    83          70 LOAD_CONST               6 (<code object GenerateOutput, file "\Python311\Lib\site-packages\pyc3dtools\pyc3dtools.py", line 83>)
+                72 MAKE_FUNCTION            0
+                74 STORE_NAME              10 (GenerateOutput)
+                76 LOAD_CONST               1 (None)
+                78 RETURN_VALUE
    consts
       0
       None
       ('tqdm',)
       ('CallbackIOWrapper',)
-      'https://c3dtools.com/API/readC3D'
       code
          argcount  : 2
-         nlocals   : 25
-         stacksize : 11
+         nlocals   : 10
+         stacksize : 8
+         flags     : 3
+         code
+            0x970064017d0264027c0069017d037401000000000000000000006a0100
+            000000000000007c01a6010000ab0100000000000000006a020000000000
+            0000007d047407000000000000000000007c016403a6020000ab02000000
+            000000000035007d057409000000000000000000007c04640464056406ac
+            07a6040000ab04000000000000000035007d06740b000000000000000000
+            007c066a0600000000000000007c056408a6030000ab0300000000000000
+            007d07740f000000000000000000006a0800000000000000007c027c0364
+            097c076901ac0aa6030000ab0300000000000000007d08640064006400a6
+            020000ab02000000000000000001006e0b23003100730477027803590077
+            010100590001000100640064006400a6020000ab02000000000000000001
+            006e0b230031007304770278035900770101005900010001000900741300
+            0000000000000000006a0a00000000000000007c086a0b00000000000000
+            00a6010000ab0100000000000000007d09640b7c097600720b7c09640b19
+            000000000000000000640c640d9c0253007419000000000000000000007c
+            09a6010000ab010000000000000000530023000100640e640c6901630259
+            005300780359007701
+           8           0 RESUME                   0
+         
+          10           2 LOAD_CONST               1 ('https://c3dtools.com/API/readC3D')
+                       4 STORE_FAST               2 (API_URL)
+         
+          11           6 LOAD_CONST               2 ('api_key')
+                       8 LOAD_FAST                0 (Token)
+                      10 BUILD_MAP                1
+                      12 STORE_FAST               3 (data)
+         
+          14          14 LOAD_GLOBAL              1 (NULL + os)
+                      26 LOAD_ATTR                1 (stat)
+                      36 LOAD_FAST                1 (file_path)
+                      38 PRECALL                  1
+                      42 CALL                     1
+                      52 LOAD_ATTR                2 (st_size)
+                      62 STORE_FAST               4 (file_size)
+         
+          15          64 LOAD_GLOBAL              7 (NULL + open)
+                      76 LOAD_FAST                1 (file_path)
+                      78 LOAD_CONST               3 ('rb')
+                      80 PRECALL                  2
+                      84 CALL                     2
+                      94 BEFORE_WITH
+                      96 STORE_FAST               5 (f)
+         
+          16          98 LOAD_GLOBAL              9 (NULL + tqdm)
+                     110 LOAD_FAST                4 (file_size)
+                     112 LOAD_CONST               4 ('B')
+                     114 LOAD_CONST               5 (True)
+                     116 LOAD_CONST               6 (1024)
+                     118 KW_NAMES                 7
+                     120 PRECALL                  4
+                     124 CALL                     4
+                     134 BEFORE_WITH
+                     136 STORE_FAST               6 (t)
+         
+          17         138 LOAD_GLOBAL             11 (NULL + CallbackIOWrapper)
+                     150 LOAD_FAST                6 (t)
+                     152 LOAD_ATTR                6 (update)
+                     162 LOAD_FAST                5 (f)
+                     164 LOAD_CONST               8 ('read')
+                     166 PRECALL                  3
+                     170 CALL                     3
+                     180 STORE_FAST               7 (wrapped_file)
+         
+          18         182 LOAD_GLOBAL             15 (NULL + requests)
+                     194 LOAD_ATTR                8 (post)
+                     204 LOAD_FAST                2 (API_URL)
+                     206 LOAD_FAST                3 (data)
+                     208 LOAD_CONST               9 ('upload_file')
+                     210 LOAD_FAST                7 (wrapped_file)
+                     212 BUILD_MAP                1
+                     214 KW_NAMES                10
+                     216 PRECALL                  3
+                     220 CALL                     3
+                     230 STORE_FAST               8 (resp)
+         
+          16         232 LOAD_CONST               0 (None)
+                     234 LOAD_CONST               0 (None)
+                     236 LOAD_CONST               0 (None)
+                     238 PRECALL                  2
+                     242 CALL                     2
+                     252 POP_TOP
+                     254 JUMP_FORWARD            11 (to 278)
+                 >>  256 PUSH_EXC_INFO
+                     258 WITH_EXCEPT_START
+                     260 POP_JUMP_FORWARD_IF_TRUE     4 (to 270)
+                     262 RERAISE                  2
+                 >>  264 COPY                     3
+                     266 POP_EXCEPT
+                     268 RERAISE                  1
+                 >>  270 POP_TOP
+                     272 POP_EXCEPT
+                     274 POP_TOP
+                     276 POP_TOP
+         
+          15     >>  278 LOAD_CONST               0 (None)
+                     280 LOAD_CONST               0 (None)
+                     282 LOAD_CONST               0 (None)
+                     284 PRECALL                  2
+                     288 CALL                     2
+                     298 POP_TOP
+                     300 JUMP_FORWARD            11 (to 324)
+                 >>  302 PUSH_EXC_INFO
+                     304 WITH_EXCEPT_START
+                     306 POP_JUMP_FORWARD_IF_TRUE     4 (to 316)
+                     308 RERAISE                  2
+                 >>  310 COPY                     3
+                     312 POP_EXCEPT
+                     314 RERAISE                  1
+                 >>  316 POP_TOP
+                     318 POP_EXCEPT
+                     320 POP_TOP
+                     322 POP_TOP
+         
+          20     >>  324 NOP
+         
+          21         326 LOAD_GLOBAL             19 (NULL + json)
+                     338 LOAD_ATTR               10 (loads)
+                     348 LOAD_FAST                8 (resp)
+                     350 LOAD_ATTR               11 (text)
+                     360 PRECALL                  1
+                     364 CALL                     1
+                     374 STORE_FAST               9 (result)
+         
+          22         376 LOAD_CONST              11 ('error_msg')
+                     378 LOAD_FAST                9 (result)
+                     380 CONTAINS_OP              0
+                     382 POP_JUMP_FORWARD_IF_FALSE    11 (to 406)
+         
+          24         384 LOAD_FAST                9 (result)
+                     386 LOAD_CONST              11 ('error_msg')
+                     388 BINARY_SUBSCR
+         
+          25         398 LOAD_CONST              12 ('Failed')
+         
+          23         400 LOAD_CONST              13 (('error', 'Status'))
+                     402 BUILD_CONST_KEY_MAP      2
+                     404 RETURN_VALUE
+         
+          29     >>  406 LOAD_GLOBAL             25 (NULL + GenerateOutput)
+                     418 LOAD_FAST                9 (result)
+                     420 PRECALL                  1
+                     424 CALL                     1
+                     434 RETURN_VALUE
+                 >>  436 PUSH_EXC_INFO
+         
+          32         438 POP_TOP
+         
+          34         440 LOAD_CONST              14 ('error')
+                     442 LOAD_CONST              12 ('Failed')
+         
+          33         444 BUILD_MAP                1
+                     446 SWAP                     2
+                     448 POP_EXCEPT
+                     450 RETURN_VALUE
+                 >>  452 COPY                     3
+                     454 POP_EXCEPT
+                     456 RERAISE                  1
+         ExceptionTable:
+           96 to 134 -> 302 [1] lasti
+           136 to 230 -> 256 [2] lasti
+           232 to 254 -> 302 [1] lasti
+           256 to 262 -> 264 [4] lasti
+           264 to 268 -> 302 [1] lasti
+           270 to 270 -> 264 [4] lasti
+           272 to 276 -> 302 [1] lasti
+           302 to 308 -> 310 [3] lasti
+           316 to 316 -> 310 [3] lasti
+           326 to 402 -> 436 [0]
+           406 to 432 -> 436 [0]
+           436 to 446 -> 452 [1] lasti
+         consts
+            None
+            'https://c3dtools.com/API/readC3D'
+            'api_key'
+            'rb'
+            'B'
+            True
+            1024
+            ('total', 'unit', 'unit_scale', 'unit_divisor')
+            'read'
+            'upload_file'
+            ('url', 'data', 'files')
+            'error_msg'
+            'Failed'
+            ('error', 'Status')
+            'error'
+         names      ('os', 'stat', 'st_size', 'open', 'tqdm', 'CallbackIOWrapper', 'update', 'requests', 'post', 'json', 'loads', 'text', 'GenerateOutput')
+         varnames   ('Token', 'file_path', 'API_URL', 'data', 'file_size', 'f', 't', 'wrapped_file', 'resp', 'result')
+         freevars   ()
+         cellvars   ()
+         filename   '\\Python311\\Lib\\site-packages\\pyc3dtools\\pyc3dtools.py'
+         name       'readC3D'
+         firstlineno 8
+         lnotab
+            0x0202040108033201220128012c0132fe2eff2e050201320108020e0102
+            fe06062003020204ff
+      code
+         argcount  : 3
+         nlocals   : 15
+         stacksize : 9
          flags     : 3
          code
-            0x8719871a871b970064017c0069017d027401000000000000000000006a
-            0100000000000000007c01a6010000ab0100000000000000006a02000000
-            00000000007d037407000000000000000000007c016402a6020000ab0200
-            0000000000000035007d047409000000000000000000007c036403640464
-            05ac06a6040000ab04000000000000000035007d05740b00000000000000
-            0000007c056a0600000000000000007c046407a6030000ab030000000000
-            0000007d06740f000000000000000000006a080000000000000000741200
-            0000000000000000007c0264087c066901ac09a6030000ab030000000000
-            0000007d07640064006400a6020000ab02000000000000000001006e0b23
-            003100730477027803590077010100590001000100640064006400a60200
-            00ab02000000000000000001006e0b230031007304770278035900770101
-            005900010001007415000000000000000000006a0b00000000000000007c
-            076a0c0000000000000000a6010000ab0100000000000000007d08090064
-            0a7c087600720a640b7c08640a19000000000000000000690153007c0864
-            0c190000000000000000008a197c08640d190000000000000000007d097c
-            08640e190000000000000000007d0a7c08640f190000000000000000007d
-            0b7c086410190000000000000000007d0c7c086411190000000000000000
-            007d0d741b000000000000000000006a0e00000000000000007c09a60100
-            00ab0100000000000000007d0e7c0e6400640085027c0a64006400850266
-            03190000000000000000007d0e7c0e7c0864123c0000007c0d0100881966
-            0164138408741f0000000000000000000074210000000000000000000089
-            19a6010000ab010000000000000000a6010000ab01000000000000000044
-            00a6000000ab0000000000000000006414190000000000000000008a1b88
-            19881b660264158408741f00000000000000000000742100000000000000
-            0000008919891b19000000000000000000641619000000000000000000a6
-            010000ab010000000000000000a6010000ab0100000000000000004400a6
-            000000ab0000000000000000006414190000000000000000007d0f881988
-            1b660264178408741f000000000000000000007421000000000000000000
-            008919891b19000000000000000000641619000000000000000000a60100
-            00ab010000000000000000a6010000ab0100000000000000004400a60000
-            00ab0000000000000000006414190000000000000000007d108819881b66
-            0264188408741f0000000000000000000074210000000000000000000089
-            19891b19000000000000000000641619000000000000000000a6010000ab
-            010000000000000000a6010000ab0100000000000000004400a6000000ab
-            0000000000000000006414190000000000000000007d118819881b660264
-            198408741f00000000000000000000742100000000000000000000891989
-            1b19000000000000000000641619000000000000000000a6010000ab0100
-            00000000000000a6010000ab0100000000000000004400a6000000ab0000
-            000000000000006414190000000000000000007d128919891b1900000000
-            00000000006416190000000000000000007c0f1900000000000000000064
-            1a190000000000000000007d138919891b19000000000000000000641619
-            0000000000000000007c1019000000000000000000641a19000000000000
-            0000006414190000000000000000007d148919891b190000000000000000
-            006416190000000000000000007c1119000000000000000000641a190000
-            000000000000006414190000000000000000007d158919891b1900000000
-            00000000006416190000000000000000007c121900000000000000000064
-            1a190000000000000000006414190000000000000000007d168819660164
-            1b8408741f000000000000000000007421000000000000000000008919a6
-            010000ab010000000000000000a6010000ab0100000000000000004400a6
-            000000ab0000000000000000006414190000000000000000008a1a881988
-            1a6602641c8408741f000000000000000000007421000000000000000000
-            008919891a19000000000000000000641619000000000000000000a60100
-            00ab010000000000000000a6010000ab0100000000000000004400a60000
-            00ab0000000000000000006414190000000000000000007d178919891a19
-            0000000000000000006416190000000000000000007c1719000000000000
-            000000641a190000000000000000007d187c0d44005d0d7d047c04641d19
-            0000000000000000007c04641e3c0000008c0e89197c0e7c097c0b7c0c7c
-            0d7c137c187c147c167c156702641f9c0a53002300742200000000000000
-            000000240072070100640b642069016302590053007700780359007701
-                       0 MAKE_CELL               25 (GP)
-                       2 MAKE_CELL               26 (gp_analog_lbl_i)
-                       4 MAKE_CELL               27 (gp_point_lbl_i)
-         
-          11           6 RESUME                   0
-         
-          13           8 LOAD_CONST               1 ('api_key')
-                      10 LOAD_FAST                0 (Token)
-                      12 BUILD_MAP                1
-                      14 STORE_FAST               2 (data)
-         
-          16          16 LOAD_GLOBAL              1 (NULL + os)
-                      28 LOAD_ATTR                1 (stat)
-                      38 LOAD_FAST                1 (file_path)
-                      40 PRECALL                  1
-                      44 CALL                     1
-                      54 LOAD_ATTR                2 (st_size)
-                      64 STORE_FAST               3 (file_size)
-         
-          17          66 LOAD_GLOBAL              7 (NULL + open)
-                      78 LOAD_FAST                1 (file_path)
-                      80 LOAD_CONST               2 ('rb')
-                      82 PRECALL                  2
-                      86 CALL                     2
-                      96 BEFORE_WITH
-                      98 STORE_FAST               4 (f)
-         
-          18         100 LOAD_GLOBAL              9 (NULL + tqdm)
-                     112 LOAD_FAST                3 (file_size)
-                     114 LOAD_CONST               3 ('B')
-                     116 LOAD_CONST               4 (True)
-                     118 LOAD_CONST               5 (1024)
-                     120 KW_NAMES                 6
-                     122 PRECALL                  4
-                     126 CALL                     4
-                     136 BEFORE_WITH
-                     138 STORE_FAST               5 (t)
-         
-          19         140 LOAD_GLOBAL             11 (NULL + CallbackIOWrapper)
-                     152 LOAD_FAST                5 (t)
-                     154 LOAD_ATTR                6 (update)
-                     164 LOAD_FAST                4 (f)
-                     166 LOAD_CONST               7 ('read')
-                     168 PRECALL                  3
-                     172 CALL                     3
-                     182 STORE_FAST               6 (wrapped_file)
-         
-          20         184 LOAD_GLOBAL             15 (NULL + requests)
-                     196 LOAD_ATTR                8 (post)
-                     206 LOAD_GLOBAL             18 (API_URL)
-                     218 LOAD_FAST                2 (data)
-                     220 LOAD_CONST               8 ('upload_file')
-                     222 LOAD_FAST                6 (wrapped_file)
-                     224 BUILD_MAP                1
-                     226 KW_NAMES                 9
+            0x970064017d0364027c0069017d047400000000000000000000006a0100
+            00000000000000a00200000000000000000000000000000000000000007c
+            01a6010000ab0100000000000000007d057401000000000000000000006a
+            0300000000000000007c01a6010000ab0100000000000000006a04000000
+            00000000007d06740b000000000000000000007c016403a6020000ab0200
+            0000000000000035007d07740d000000000000000000007c066404640564
+            06ac07a6040000ab04000000000000000035007d08740f00000000000000
+            0000007c086a0800000000000000007c076408a6030000ab030000000000
+            0000007d097413000000000000000000006a0a00000000000000007c0364
+            057c0464097c096901ac0aa6040000ab0400000000000000007d0a640064
+            006400a6020000ab02000000000000000001006e0b230031007304770278
+            03590077010100590001000100640064006400a6020000ab020000000000
+            00000001006e0b2300310073047702780359007701010059000100010009
+            007417000000000000000000006a0c00000000000000007c0a6a0d000000
+            0000000000a6010000ab0100000000000000007d0b640b7c0b7600720b7c
+            0b640b19000000000000000000640c640d9c025300640e7c0b7600729d74
+            0b000000000000000000007c02640f7a0000007c05640064108502190000
+            000000000000007a000000640e7a0000006411a6020000ab020000000000
+            0000007d0c7c0ca00e00000000000000000000000000000000000000007c
+            0b640e19000000000000000000641219000000000000000000a6010000ab
+            01000000000000000001007c0ca00e000000000000000000000000000000
+            00000000007c0b640e190000000000000000006413190000000000000000
+            00a6010000ab01000000000000000001007c0b640e190000000000000000
+            0064141900000000000000000044005d177d0d7c0ca00e00000000000000
+            000000000000000000000000007c0da6010000ab01000000000000000001
+            008c187c0ca00f0000000000000000000000000000000000000000a60000
+            00ab000000000000000000010064157c0b760090017200740b0000000000
+            00000000007c02640f7a0000007c05640064108502190000000000000000
+            007a00000064157a0000006411a6020000ab0200000000000000007d0e7c
+            0ea00e00000000000000000000000000000000000000007c0b6415190000
+            00000000000000641219000000000000000000a6010000ab010000000000
+            00000001007c0ea00e00000000000000000000000000000000000000007c
+            0b641519000000000000000000641319000000000000000000a6010000ab
+            01000000000000000001007c0ea00e000000000000000000000000000000
+            00000000007c0b6415190000000000000000006416190000000000000000
+            00a6010000ab01000000000000000001007c0ea00e000000000000000000
+            00000000000000000000007c0b6415190000000000000000006417190000
+            00000000000000a6010000ab01000000000000000001007c0ea00e000000
+            00000000000000000000000000000000007c0b6415190000000000000000
+            00641819000000000000000000a6010000ab01000000000000000001007c
+            0b64151900000000000000000064141900000000000000000044005d177d
+            0d7c0ea00e00000000000000000000000000000000000000007c0da60100
+            00ab01000000000000000001008c187c0ea00f0000000000000000000000
+            000000000000000000a6000000ab00000000000000000001007421000000
+            000000000000007c0b641919000000000000000000a6010000ab01000000
+            0000000000530023000100641a640c6901630259005300780359007701
+          38           0 RESUME                   0
+         
+          39           2 LOAD_CONST               1 ('https://c3dtools.com/API/getOpenSimData')
+                       4 STORE_FAST               3 (API_URL)
+         
+          40           6 LOAD_CONST               2 ('api_key')
+                       8 LOAD_FAST                0 (Token)
+                      10 BUILD_MAP                1
+                      12 STORE_FAST               4 (data)
+         
+          41          14 LOAD_GLOBAL              0 (os)
+                      26 LOAD_ATTR                1 (path)
+                      36 LOAD_METHOD              2 (basename)
+                      58 LOAD_FAST                1 (file_path)
+                      60 PRECALL                  1
+                      64 CALL                     1
+                      74 STORE_FAST               5 (file_name)
+         
+          42          76 LOAD_GLOBAL              1 (NULL + os)
+                      88 LOAD_ATTR                3 (stat)
+                      98 LOAD_FAST                1 (file_path)
+                     100 PRECALL                  1
+                     104 CALL                     1
+                     114 LOAD_ATTR                4 (st_size)
+                     124 STORE_FAST               6 (file_size)
+         
+          43         126 LOAD_GLOBAL             11 (NULL + open)
+                     138 LOAD_FAST                1 (file_path)
+                     140 LOAD_CONST               3 ('rb')
+                     142 PRECALL                  2
+                     146 CALL                     2
+                     156 BEFORE_WITH
+                     158 STORE_FAST               7 (f)
+         
+          44         160 LOAD_GLOBAL             13 (NULL + tqdm)
+                     172 LOAD_FAST                6 (file_size)
+                     174 LOAD_CONST               4 ('B')
+                     176 LOAD_CONST               5 (True)
+                     178 LOAD_CONST               6 (1024)
+                     180 KW_NAMES                 7
+                     182 PRECALL                  4
+                     186 CALL                     4
+                     196 BEFORE_WITH
+                     198 STORE_FAST               8 (t)
+         
+          45         200 LOAD_GLOBAL             15 (NULL + CallbackIOWrapper)
+                     212 LOAD_FAST                8 (t)
+                     214 LOAD_ATTR                8 (update)
+                     224 LOAD_FAST                7 (f)
+                     226 LOAD_CONST               8 ('read')
                      228 PRECALL                  3
                      232 CALL                     3
-                     242 STORE_FAST               7 (resp)
+                     242 STORE_FAST               9 (wrapped_file)
          
-          18         244 LOAD_CONST               0 (None)
-                     246 LOAD_CONST               0 (None)
-                     248 LOAD_CONST               0 (None)
-                     250 PRECALL                  2
-                     254 CALL                     2
-                     264 POP_TOP
-                     266 JUMP_FORWARD            11 (to 290)
-                 >>  268 PUSH_EXC_INFO
-                     270 WITH_EXCEPT_START
-                     272 POP_JUMP_FORWARD_IF_TRUE     4 (to 282)
-                     274 RERAISE                  2
-                 >>  276 COPY                     3
-                     278 POP_EXCEPT
-                     280 RERAISE                  1
-                 >>  282 POP_TOP
-                     284 POP_EXCEPT
-                     286 POP_TOP
-                     288 POP_TOP
-         
-          17     >>  290 LOAD_CONST               0 (None)
-                     292 LOAD_CONST               0 (None)
-                     294 LOAD_CONST               0 (None)
-                     296 PRECALL                  2
-                     300 CALL                     2
-                     310 POP_TOP
-                     312 JUMP_FORWARD            11 (to 336)
-                 >>  314 PUSH_EXC_INFO
-                     316 WITH_EXCEPT_START
-                     318 POP_JUMP_FORWARD_IF_TRUE     4 (to 328)
-                     320 RERAISE                  2
-                 >>  322 COPY                     3
-                     324 POP_EXCEPT
-                     326 RERAISE                  1
-                 >>  328 POP_TOP
+          46         244 LOAD_GLOBAL             19 (NULL + requests)
+                     256 LOAD_ATTR               10 (post)
+                     266 LOAD_FAST                3 (API_URL)
+                     268 LOAD_CONST               5 (True)
+                     270 LOAD_FAST                4 (data)
+                     272 LOAD_CONST               9 ('upload_file')
+                     274 LOAD_FAST                9 (wrapped_file)
+                     276 BUILD_MAP                1
+                     278 KW_NAMES                10
+                     280 PRECALL                  4
+                     284 CALL                     4
+                     294 STORE_FAST              10 (resp)
+         
+          44         296 LOAD_CONST               0 (None)
+                     298 LOAD_CONST               0 (None)
+                     300 LOAD_CONST               0 (None)
+                     302 PRECALL                  2
+                     306 CALL                     2
+                     316 POP_TOP
+                     318 JUMP_FORWARD            11 (to 342)
+                 >>  320 PUSH_EXC_INFO
+                     322 WITH_EXCEPT_START
+                     324 POP_JUMP_FORWARD_IF_TRUE     4 (to 334)
+                     326 RERAISE                  2
+                 >>  328 COPY                     3
                      330 POP_EXCEPT
-                     332 POP_TOP
-                     334 POP_TOP
-         
-          23     >>  336 LOAD_GLOBAL             21 (NULL + json)
-                     348 LOAD_ATTR               11 (loads)
-                     358 LOAD_FAST                7 (resp)
-                     360 LOAD_ATTR               12 (text)
-                     370 PRECALL                  1
-                     374 CALL                     1
-                     384 STORE_FAST               8 (result)
-         
-          25         386 NOP
-         
-          26         388 LOAD_CONST              10 ('error_msg')
-                     390 LOAD_FAST                8 (result)
-                     392 CONTAINS_OP              0
-                     394 POP_JUMP_FORWARD_IF_FALSE    10 (to 416)
-         
-          28         396 LOAD_CONST              11 ('error')
-                     398 LOAD_FAST                8 (result)
-                     400 LOAD_CONST              10 ('error_msg')
-                     402 BINARY_SUBSCR
-         
-          27         412 BUILD_MAP                1
-                     414 RETURN_VALUE
-         
-          32     >>  416 LOAD_FAST                8 (result)
-                     418 LOAD_CONST              12 ('GP')
-                     420 BINARY_SUBSCR
-                     430 STORE_DEREF             25 (GP)
-         
-          33         432 LOAD_FAST                8 (result)
-                     434 LOAD_CONST              13 ('Point')
-                     436 BINARY_SUBSCR
-                     446 STORE_FAST               9 (Point)
+                     332 RERAISE                  1
+                 >>  334 POP_TOP
+                     336 POP_EXCEPT
+                     338 POP_TOP
+                     340 POP_TOP
+         
+          43     >>  342 LOAD_CONST               0 (None)
+                     344 LOAD_CONST               0 (None)
+                     346 LOAD_CONST               0 (None)
+                     348 PRECALL                  2
+                     352 CALL                     2
+                     362 POP_TOP
+                     364 JUMP_FORWARD            11 (to 388)
+                 >>  366 PUSH_EXC_INFO
+                     368 WITH_EXCEPT_START
+                     370 POP_JUMP_FORWARD_IF_TRUE     4 (to 380)
+                     372 RERAISE                  2
+                 >>  374 COPY                     3
+                     376 POP_EXCEPT
+                     378 RERAISE                  1
+                 >>  380 POP_TOP
+                     382 POP_EXCEPT
+                     384 POP_TOP
+                     386 POP_TOP
+         
+          48     >>  388 NOP
+         
+          49         390 LOAD_GLOBAL             23 (NULL + json)
+                     402 LOAD_ATTR               12 (loads)
+                     412 LOAD_FAST               10 (resp)
+                     414 LOAD_ATTR               13 (text)
+                     424 PRECALL                  1
+                     428 CALL                     1
+                     438 STORE_FAST              11 (result)
+         
+          51         440 LOAD_CONST              11 ('error_msg')
+                     442 LOAD_FAST               11 (result)
+                     444 CONTAINS_OP              0
+                     446 POP_JUMP_FORWARD_IF_FALSE    11 (to 470)
          
-          34         448 LOAD_FAST                8 (result)
-                     450 LOAD_CONST              14 ('Real_marker_index')
+          52         448 LOAD_FAST               11 (result)
+                     450 LOAD_CONST              11 ('error_msg')
                      452 BINARY_SUBSCR
-                     462 STORE_FAST              10 (Real_marker_index)
-         
-          35         464 LOAD_FAST                8 (result)
-                     466 LOAD_CONST              15 ('Analog')
-                     468 BINARY_SUBSCR
-                     478 STORE_FAST              11 (Analog)
-         
-          36         480 LOAD_FAST                8 (result)
-                     482 LOAD_CONST              16 ('Header')
-                     484 BINARY_SUBSCR
-                     494 STORE_FAST              12 (Header)
-         
-          37         496 LOAD_FAST                8 (result)
-                     498 LOAD_CONST              17 ('Forceplate_list')
-                     500 BINARY_SUBSCR
-                     510 STORE_FAST              13 (Forceplates)
-         
-          38         512 LOAD_GLOBAL             27 (NULL + np)
-                     524 LOAD_ATTR               14 (array)
-                     534 LOAD_FAST                9 (Point)
-                     536 PRECALL                  1
-                     540 CALL                     1
-                     550 STORE_FAST              14 (Real_Markers)
-         
-          39         552 LOAD_FAST               14 (Real_Markers)
-                     554 LOAD_CONST               0 (None)
-                     556 LOAD_CONST               0 (None)
-                     558 BUILD_SLICE              2
-                     560 LOAD_FAST               10 (Real_marker_index)
-                     562 LOAD_CONST               0 (None)
-                     564 LOAD_CONST               0 (None)
-                     566 BUILD_SLICE              2
-                     568 BUILD_TUPLE              3
-                     570 BINARY_SUBSCR
-                     580 STORE_FAST              14 (Real_Markers)
-         
-          40         582 LOAD_FAST               14 (Real_Markers)
-                     584 LOAD_FAST                8 (result)
-                     586 LOAD_CONST              18 ('Markers')
-                     588 STORE_SUBSCR
-         
-          44         592 LOAD_FAST               13 (Forceplates)
-                     594 POP_TOP
-         
-          48         596 LOAD_CLOSURE            25 (GP)
-                     598 BUILD_TUPLE              1
-                     600 LOAD_CONST              19 (<code object <listcomp>, file "\Python311\Lib\site-packages\pyc3dtools\pyc3dtools.py", line 48>)
-                     602 MAKE_FUNCTION            8 (closure)
-         
-          49         604 LOAD_GLOBAL             31 (NULL + range)
-                     616 LOAD_GLOBAL             33 (NULL + len)
-                     628 LOAD_DEREF              25 (GP)
-                     630 PRECALL                  1
-                     634 CALL                     1
-                     644 PRECALL                  1
-                     648 CALL                     1
-         
-          48         658 GET_ITER
-                     660 PRECALL                  0
-                     664 CALL                     0
-         
-          51         674 LOAD_CONST              20 (0)
-         
-          48         676 BINARY_SUBSCR
-                     686 STORE_DEREF             27 (gp_point_lbl_i)
-         
-          52         688 LOAD_CLOSURE            25 (GP)
-                     690 LOAD_CLOSURE            27 (gp_point_lbl_i)
-                     692 BUILD_TUPLE              2
-                     694 LOAD_CONST              21 (<code object <listcomp>, file "\Python311\Lib\site-packages\pyc3dtools\pyc3dtools.py", line 52>)
-                     696 MAKE_FUNCTION            8 (closure)
-         
-          53         698 LOAD_GLOBAL             31 (NULL + range)
-                     710 LOAD_GLOBAL             33 (NULL + len)
-                     722 LOAD_DEREF              25 (GP)
-                     724 LOAD_DEREF              27 (gp_point_lbl_i)
-                     726 BINARY_SUBSCR
-                     736 LOAD_CONST              22 ('List_Parameters')
-                     738 BINARY_SUBSCR
-                     748 PRECALL                  1
-                     752 CALL                     1
-                     762 PRECALL                  1
-                     766 CALL                     1
-         
-          52         776 GET_ITER
-                     778 PRECALL                  0
-                     782 CALL                     0
-         
-          55         792 LOAD_CONST              20 (0)
-         
-          52         794 BINARY_SUBSCR
-                     804 STORE_FAST              15 (gp_point_lbl_ii)
-         
-          56         806 LOAD_CLOSURE            25 (GP)
-                     808 LOAD_CLOSURE            27 (gp_point_lbl_i)
-                     810 BUILD_TUPLE              2
-                     812 LOAD_CONST              23 (<code object <listcomp>, file "\Python311\Lib\site-packages\pyc3dtools\pyc3dtools.py", line 56>)
-                     814 MAKE_FUNCTION            8 (closure)
-         
-          57         816 LOAD_GLOBAL             31 (NULL + range)
-                     828 LOAD_GLOBAL             33 (NULL + len)
-                     840 LOAD_DEREF              25 (GP)
-                     842 LOAD_DEREF              27 (gp_point_lbl_i)
-                     844 BINARY_SUBSCR
-                     854 LOAD_CONST              22 ('List_Parameters')
-                     856 BINARY_SUBSCR
-                     866 PRECALL                  1
-                     870 CALL                     1
-                     880 PRECALL                  1
-                     884 CALL                     1
-         
-          56         894 GET_ITER
-                     896 PRECALL                  0
-                     900 CALL                     0
-         
-          59         910 LOAD_CONST              20 (0)
-         
-          56         912 BINARY_SUBSCR
-                     922 STORE_FAST              16 (gp_point_unit_i)
-         
-          60         924 LOAD_CLOSURE            25 (GP)
-                     926 LOAD_CLOSURE            27 (gp_point_lbl_i)
-                     928 BUILD_TUPLE              2
-                     930 LOAD_CONST              24 (<code object <listcomp>, file "\Python311\Lib\site-packages\pyc3dtools\pyc3dtools.py", line 60>)
-                     932 MAKE_FUNCTION            8 (closure)
-         
-          61         934 LOAD_GLOBAL             31 (NULL + range)
-                     946 LOAD_GLOBAL             33 (NULL + len)
-                     958 LOAD_DEREF              25 (GP)
-                     960 LOAD_DEREF              27 (gp_point_lbl_i)
+                     462 LOAD_CONST              12 ('Failed')
+                     464 LOAD_CONST              13 (('error', 'Status'))
+                     466 BUILD_CONST_KEY_MAP      2
+                     468 RETURN_VALUE
+         
+          55     >>  470 LOAD_CONST              14 ('mot')
+                     472 LOAD_FAST               11 (result)
+                     474 CONTAINS_OP              0
+                     476 POP_JUMP_FORWARD_IF_FALSE   157 (to 792)
+         
+          56         478 LOAD_GLOBAL             11 (NULL + open)
+                     490 LOAD_FAST                2 (des_path)
+                     492 LOAD_CONST              15 ('/')
+                     494 BINARY_OP                0 (+)
+                     498 LOAD_FAST                5 (file_name)
+                     500 LOAD_CONST               0 (None)
+                     502 LOAD_CONST              16 (-3)
+                     504 BUILD_SLICE              2
+                     506 BINARY_SUBSCR
+                     516 BINARY_OP                0 (+)
+                     520 LOAD_CONST              14 ('mot')
+                     522 BINARY_OP                0 (+)
+                     526 LOAD_CONST              17 ('w')
+                     528 PRECALL                  2
+                     532 CALL                     2
+                     542 STORE_FAST              12 (motFile)
+         
+          57         544 LOAD_FAST               12 (motFile)
+                     546 LOAD_METHOD             14 (writelines)
+                     568 LOAD_FAST               11 (result)
+                     570 LOAD_CONST              14 ('mot')
+                     572 BINARY_SUBSCR
+                     582 LOAD_CONST              18 ('h1')
+                     584 BINARY_SUBSCR
+                     594 PRECALL                  1
+                     598 CALL                     1
+                     608 POP_TOP
+         
+          58         610 LOAD_FAST               12 (motFile)
+                     612 LOAD_METHOD             14 (writelines)
+                     634 LOAD_FAST               11 (result)
+                     636 LOAD_CONST              14 ('mot')
+                     638 BINARY_SUBSCR
+                     648 LOAD_CONST              19 ('h2')
+                     650 BINARY_SUBSCR
+                     660 PRECALL                  1
+                     664 CALL                     1
+                     674 POP_TOP
+         
+          59         676 LOAD_FAST               11 (result)
+                     678 LOAD_CONST              14 ('mot')
+                     680 BINARY_SUBSCR
+                     690 LOAD_CONST              20 ('data')
+                     692 BINARY_SUBSCR
+                     702 GET_ITER
+                 >>  704 FOR_ITER                23 (to 752)
+                     706 STORE_FAST              13 (d)
+         
+          60         708 LOAD_FAST               12 (motFile)
+                     710 LOAD_METHOD             14 (writelines)
+                     732 LOAD_FAST               13 (d)
+                     734 PRECALL                  1
+                     738 CALL                     1
+                     748 POP_TOP
+                     750 JUMP_BACKWARD           24 (to 704)
+         
+          61     >>  752 LOAD_FAST               12 (motFile)
+                     754 LOAD_METHOD             15 (close)
+                     776 PRECALL                  0
+                     780 CALL                     0
+                     790 POP_TOP
+         
+          63     >>  792 LOAD_CONST              21 ('trc')
+                     794 LOAD_FAST               11 (result)
+                     796 CONTAINS_OP              0
+                     798 EXTENDED_ARG             1
+                     800 POP_JUMP_FORWARD_IF_FALSE   256 (to 1314)
+         
+          64         802 LOAD_GLOBAL             11 (NULL + open)
+                     814 LOAD_FAST                2 (des_path)
+                     816 LOAD_CONST              15 ('/')
+                     818 BINARY_OP                0 (+)
+                     822 LOAD_FAST                5 (file_name)
+                     824 LOAD_CONST               0 (None)
+                     826 LOAD_CONST              16 (-3)
+                     828 BUILD_SLICE              2
+                     830 BINARY_SUBSCR
+                     840 BINARY_OP                0 (+)
+                     844 LOAD_CONST              21 ('trc')
+                     846 BINARY_OP                0 (+)
+                     850 LOAD_CONST              17 ('w')
+                     852 PRECALL                  2
+                     856 CALL                     2
+                     866 STORE_FAST              14 (trcFile)
+         
+          65         868 LOAD_FAST               14 (trcFile)
+                     870 LOAD_METHOD             14 (writelines)
+                     892 LOAD_FAST               11 (result)
+                     894 LOAD_CONST              21 ('trc')
+                     896 BINARY_SUBSCR
+                     906 LOAD_CONST              18 ('h1')
+                     908 BINARY_SUBSCR
+                     918 PRECALL                  1
+                     922 CALL                     1
+                     932 POP_TOP
+         
+          66         934 LOAD_FAST               14 (trcFile)
+                     936 LOAD_METHOD             14 (writelines)
+                     958 LOAD_FAST               11 (result)
+                     960 LOAD_CONST              21 ('trc')
                      962 BINARY_SUBSCR
-                     972 LOAD_CONST              22 ('List_Parameters')
+                     972 LOAD_CONST              19 ('h2')
                      974 BINARY_SUBSCR
                      984 PRECALL                  1
                      988 CALL                     1
-                     998 PRECALL                  1
-                    1002 CALL                     1
+                     998 POP_TOP
          
-          60        1012 GET_ITER
-                    1014 PRECALL                  0
-                    1018 CALL                     0
-         
-          63        1028 LOAD_CONST              20 (0)
-         
-          60        1030 BINARY_SUBSCR
-                    1040 STORE_FAST              17 (gp_point_Yscreen_i)
-         
-          64        1042 LOAD_CLOSURE            25 (GP)
-                    1044 LOAD_CLOSURE            27 (gp_point_lbl_i)
-                    1046 BUILD_TUPLE              2
-                    1048 LOAD_CONST              25 (<code object <listcomp>, file "\Python311\Lib\site-packages\pyc3dtools\pyc3dtools.py", line 64>)
-                    1050 MAKE_FUNCTION            8 (closure)
-         
-          65        1052 LOAD_GLOBAL             31 (NULL + range)
-                    1064 LOAD_GLOBAL             33 (NULL + len)
-                    1076 LOAD_DEREF              25 (GP)
-                    1078 LOAD_DEREF              27 (gp_point_lbl_i)
-                    1080 BINARY_SUBSCR
-                    1090 LOAD_CONST              22 ('List_Parameters')
-                    1092 BINARY_SUBSCR
-                    1102 PRECALL                  1
-                    1106 CALL                     1
+          67        1000 LOAD_FAST               14 (trcFile)
+                    1002 LOAD_METHOD             14 (writelines)
+                    1024 LOAD_FAST               11 (result)
+                    1026 LOAD_CONST              21 ('trc')
+                    1028 BINARY_SUBSCR
+                    1038 LOAD_CONST              22 ('h3')
+                    1040 BINARY_SUBSCR
+                    1050 PRECALL                  1
+                    1054 CALL                     1
+                    1064 POP_TOP
+         
+          68        1066 LOAD_FAST               14 (trcFile)
+                    1068 LOAD_METHOD             14 (writelines)
+                    1090 LOAD_FAST               11 (result)
+                    1092 LOAD_CONST              21 ('trc')
+                    1094 BINARY_SUBSCR
+                    1104 LOAD_CONST              23 ('h4')
+                    1106 BINARY_SUBSCR
                     1116 PRECALL                  1
                     1120 CALL                     1
+                    1130 POP_TOP
          
-          64        1130 GET_ITER
-                    1132 PRECALL                  0
-                    1136 CALL                     0
-         
-          67        1146 LOAD_CONST              20 (0)
-         
-          64        1148 BINARY_SUBSCR
-                    1158 STORE_FAST              18 (gp_point_Xscreen_i)
-         
-          68        1160 LOAD_DEREF              25 (GP)
-                    1162 LOAD_DEREF              27 (gp_point_lbl_i)
-                    1164 BINARY_SUBSCR
-                    1174 LOAD_CONST              22 ('List_Parameters')
-                    1176 BINARY_SUBSCR
-                    1186 LOAD_FAST               15 (gp_point_lbl_ii)
-                    1188 BINARY_SUBSCR
-                    1198 LOAD_CONST              26 ('Param_data')
-                    1200 BINARY_SUBSCR
-                    1210 STORE_FAST              19 (Markers_lbl)
-         
-          69        1212 LOAD_DEREF              25 (GP)
-                    1214 LOAD_DEREF              27 (gp_point_lbl_i)
-                    1216 BINARY_SUBSCR
-                    1226 LOAD_CONST              22 ('List_Parameters')
-                    1228 BINARY_SUBSCR
-                    1238 LOAD_FAST               16 (gp_point_unit_i)
-                    1240 BINARY_SUBSCR
-                    1250 LOAD_CONST              26 ('Param_data')
-                    1252 BINARY_SUBSCR
-                    1262 LOAD_CONST              20 (0)
-                    1264 BINARY_SUBSCR
-                    1274 STORE_FAST              20 (Markers_Units)
-         
-          70        1276 LOAD_DEREF              25 (GP)
-                    1278 LOAD_DEREF              27 (gp_point_lbl_i)
-                    1280 BINARY_SUBSCR
-                    1290 LOAD_CONST              22 ('List_Parameters')
-                    1292 BINARY_SUBSCR
-                    1302 LOAD_FAST               17 (gp_point_Yscreen_i)
-                    1304 BINARY_SUBSCR
-                    1314 LOAD_CONST              26 ('Param_data')
-                    1316 BINARY_SUBSCR
-                    1326 LOAD_CONST              20 (0)
-                    1328 BINARY_SUBSCR
-                    1338 STORE_FAST              21 (Markers_YSCREEN)
-         
-          71        1340 LOAD_DEREF              25 (GP)
-                    1342 LOAD_DEREF              27 (gp_point_lbl_i)
-                    1344 BINARY_SUBSCR
-                    1354 LOAD_CONST              22 ('List_Parameters')
-                    1356 BINARY_SUBSCR
-                    1366 LOAD_FAST               18 (gp_point_Xscreen_i)
-                    1368 BINARY_SUBSCR
-                    1378 LOAD_CONST              26 ('Param_data')
-                    1380 BINARY_SUBSCR
-                    1390 LOAD_CONST              20 (0)
-                    1392 BINARY_SUBSCR
-                    1402 STORE_FAST              22 (Markers_XSCREEN)
-         
-          74        1404 LOAD_CLOSURE            25 (GP)
-                    1406 BUILD_TUPLE              1
-                    1408 LOAD_CONST              27 (<code object <listcomp>, file "\Python311\Lib\site-packages\pyc3dtools\pyc3dtools.py", line 74>)
-                    1410 MAKE_FUNCTION            8 (closure)
-         
-          75        1412 LOAD_GLOBAL             31 (NULL + range)
-                    1424 LOAD_GLOBAL             33 (NULL + len)
-                    1436 LOAD_DEREF              25 (GP)
-                    1438 PRECALL                  1
-                    1442 CALL                     1
-                    1452 PRECALL                  1
-                    1456 CALL                     1
-         
-          74        1466 GET_ITER
-                    1468 PRECALL                  0
-                    1472 CALL                     0
-         
-          77        1482 LOAD_CONST              20 (0)
-         
-          74        1484 BINARY_SUBSCR
-                    1494 STORE_DEREF             26 (gp_analog_lbl_i)
-         
-          78        1496 LOAD_CLOSURE            25 (GP)
-                    1498 LOAD_CLOSURE            26 (gp_analog_lbl_i)
-                    1500 BUILD_TUPLE              2
-                    1502 LOAD_CONST              28 (<code object <listcomp>, file "\Python311\Lib\site-packages\pyc3dtools\pyc3dtools.py", line 78>)
-                    1504 MAKE_FUNCTION            8 (closure)
-         
-          79        1506 LOAD_GLOBAL             31 (NULL + range)
-                    1518 LOAD_GLOBAL             33 (NULL + len)
-                    1530 LOAD_DEREF              25 (GP)
-                    1532 LOAD_DEREF              26 (gp_analog_lbl_i)
-                    1534 BINARY_SUBSCR
-                    1544 LOAD_CONST              22 ('List_Parameters')
-                    1546 BINARY_SUBSCR
-                    1556 PRECALL                  1
-                    1560 CALL                     1
-                    1570 PRECALL                  1
-                    1574 CALL                     1
-         
-          78        1584 GET_ITER
-                    1586 PRECALL                  0
-                    1590 CALL                     0
-         
-          81        1600 LOAD_CONST              20 (0)
-         
-          78        1602 BINARY_SUBSCR
-                    1612 STORE_FAST              23 (gp_analog_lbl_ii)
-         
-          82        1614 LOAD_DEREF              25 (GP)
-                    1616 LOAD_DEREF              26 (gp_analog_lbl_i)
-                    1618 BINARY_SUBSCR
-                    1628 LOAD_CONST              22 ('List_Parameters')
-                    1630 BINARY_SUBSCR
-                    1640 LOAD_FAST               23 (gp_analog_lbl_ii)
-                    1642 BINARY_SUBSCR
-                    1652 LOAD_CONST              26 ('Param_data')
-                    1654 BINARY_SUBSCR
-                    1664 STORE_FAST              24 (Analog_lbl)
-         
-          87        1666 LOAD_FAST               13 (Forceplates)
-                    1668 GET_ITER
-                 >> 1670 FOR_ITER                13 (to 1698)
-                    1672 STORE_FAST               4 (f)
-         
-          88        1674 LOAD_FAST                4 (f)
-                    1676 LOAD_CONST              29 ('orgin')
-                    1678 BINARY_SUBSCR
-                    1688 LOAD_FAST                4 (f)
-                    1690 LOAD_CONST              30 ('Origin')
-                    1692 STORE_SUBSCR
-                    1696 JUMP_BACKWARD           14 (to 1670)
-         
-          91     >> 1698 LOAD_DEREF              25 (GP)
-         
-          92        1700 LOAD_FAST               14 (Real_Markers)
-         
-          93        1702 LOAD_FAST                9 (Point)
-         
-          94        1704 LOAD_FAST               11 (Analog)
-         
-          95        1706 LOAD_FAST               12 (Header)
-         
-          96        1708 LOAD_FAST               13 (Forceplates)
-         
-          97        1710 LOAD_FAST               19 (Markers_lbl)
-         
-          98        1712 LOAD_FAST               24 (Analog_lbl)
-         
-          99        1714 LOAD_FAST               20 (Markers_Units)
-         
-         100        1716 LOAD_FAST               22 (Markers_XSCREEN)
-                    1718 LOAD_FAST               21 (Markers_YSCREEN)
-                    1720 BUILD_LIST               2
-         
-          90        1722 LOAD_CONST              31 (('GP', 'Markers', 'Points', 'Analog', 'Header', 'ForcePlate', 'Markers Label', 'Analog Label', 'Units', 'Coordinate system'))
-                    1724 BUILD_CONST_KEY_MAP     10
-                    1726 RETURN_VALUE
-                 >> 1728 PUSH_EXC_INFO
-         
-         102        1730 LOAD_GLOBAL             34 (KeyError)
-                    1742 CHECK_EXC_MATCH
-                    1744 POP_JUMP_FORWARD_IF_FALSE     7 (to 1760)
-                    1746 POP_TOP
-         
-         104        1748 LOAD_CONST              11 ('error')
-                    1750 LOAD_CONST              32 ('Failed')
-         
-         103        1752 BUILD_MAP                1
-                    1754 SWAP                     2
-                    1756 POP_EXCEPT
-                    1758 RETURN_VALUE
-         
-         102     >> 1760 RERAISE                  0
-                 >> 1762 COPY                     3
-                    1764 POP_EXCEPT
-                    1766 RERAISE                  1
+          69        1132 LOAD_FAST               14 (trcFile)
+                    1134 LOAD_METHOD             14 (writelines)
+                    1156 LOAD_FAST               11 (result)
+                    1158 LOAD_CONST              21 ('trc')
+                    1160 BINARY_SUBSCR
+                    1170 LOAD_CONST              24 ('h5')
+                    1172 BINARY_SUBSCR
+                    1182 PRECALL                  1
+                    1186 CALL                     1
+                    1196 POP_TOP
+         
+          70        1198 LOAD_FAST               11 (result)
+                    1200 LOAD_CONST              21 ('trc')
+                    1202 BINARY_SUBSCR
+                    1212 LOAD_CONST              20 ('data')
+                    1214 BINARY_SUBSCR
+                    1224 GET_ITER
+                 >> 1226 FOR_ITER                23 (to 1274)
+                    1228 STORE_FAST              13 (d)
+         
+          71        1230 LOAD_FAST               14 (trcFile)
+                    1232 LOAD_METHOD             14 (writelines)
+                    1254 LOAD_FAST               13 (d)
+                    1256 PRECALL                  1
+                    1260 CALL                     1
+                    1270 POP_TOP
+                    1272 JUMP_BACKWARD           24 (to 1226)
+         
+          72     >> 1274 LOAD_FAST               14 (trcFile)
+                    1276 LOAD_METHOD             15 (close)
+                    1298 PRECALL                  0
+                    1302 CALL                     0
+                    1312 POP_TOP
+         
+          74     >> 1314 LOAD_GLOBAL             33 (NULL + GenerateOutput)
+                    1326 LOAD_FAST               11 (result)
+                    1328 LOAD_CONST              25 ('c3d')
+                    1330 BINARY_SUBSCR
+                    1340 PRECALL                  1
+                    1344 CALL                     1
+                    1354 RETURN_VALUE
+                 >> 1356 PUSH_EXC_INFO
+         
+          76        1358 POP_TOP
+         
+          77        1360 LOAD_CONST              26 ('Status')
+                    1362 LOAD_CONST              12 ('Failed')
+                    1364 BUILD_MAP                1
+                    1366 SWAP                     2
+                    1368 POP_EXCEPT
+                    1370 RETURN_VALUE
+                 >> 1372 COPY                     3
+                    1374 POP_EXCEPT
+                    1376 RERAISE                  1
          ExceptionTable:
-           98 to 136 -> 314 [1] lasti
-           138 to 242 -> 268 [2] lasti
-           244 to 266 -> 314 [1] lasti
-           268 to 274 -> 276 [4] lasti
-           276 to 280 -> 314 [1] lasti
-           282 to 282 -> 276 [4] lasti
-           284 to 288 -> 314 [1] lasti
-           314 to 320 -> 322 [3] lasti
-           328 to 328 -> 322 [3] lasti
-           388 to 412 -> 1728 [0]
-           416 to 1724 -> 1728 [0]
-           1728 to 1754 -> 1762 [1] lasti
-           1760 to 1760 -> 1762 [1] lasti
+           158 to 196 -> 366 [1] lasti
+           198 to 294 -> 320 [2] lasti
+           296 to 318 -> 366 [1] lasti
+           320 to 326 -> 328 [4] lasti
+           328 to 332 -> 366 [1] lasti
+           334 to 334 -> 328 [4] lasti
+           336 to 340 -> 366 [1] lasti
+           366 to 372 -> 374 [3] lasti
+           380 to 380 -> 374 [3] lasti
+           390 to 466 -> 1356 [0]
+           470 to 1352 -> 1356 [0]
+           1356 to 1366 -> 1372 [1] lasti
          consts
             None
+            'https://c3dtools.com/API/getOpenSimData'
             'api_key'
             'rb'
             'B'
             True
             1024
             ('total', 'unit', 'unit_scale', 'unit_divisor')
             'read'
             'upload_file'
-            ('url', 'data', 'files')
+            ('url', 'stream', 'data', 'files')
             'error_msg'
-            'error'
+            'Failed'
+            ('error', 'Status')
+            'mot'
+            '/'
+            -3
+            'w'
+            'h1'
+            'h2'
+            'data'
+            'trc'
+            'h3'
+            'h4'
+            'h5'
+            'c3d'
+            'Status'
+         names      ('os', 'path', 'basename', 'stat', 'st_size', 'open', 'tqdm', 'CallbackIOWrapper', 'update', 'requests', 'post', 'json', 'loads', 'text', 'writelines', 'close', 'GenerateOutput')
+         varnames   ('Token', 'file_path', 'des_path', 'API_URL', 'data', 'file_name', 'file_size', 'f', 't', 'wrapped_file', 'resp', 'result', 'motFile', 'd', 'trcFile')
+         freevars   ()
+         cellvars   ()
+         filename   '\\Python311\\Lib\\site-packages\\pyc3dtools\\pyc3dtools.py'
+         name       'getTRCMot'
+         firstlineno 38
+         lnotab
+            0x0201040108013e013201220128012c0134fe2eff2e0502013202080116
+            03080142014201420120012c0128020a0142014201420142014201420120
+            012c0128022c020201
+      code
+         argcount  : 1
+         nlocals   : 18
+         stacksize : 12
+         flags     : 3
+         code
+            0x87128713871497007c006401190000000000000000008a127c00640219
+            0000000000000000007d017c006403190000000000000000007d027c0064
+            04190000000000000000007d037c006405190000000000000000007d047c
+            006406190000000000000000007d057401000000000000000000006a0100
+            000000000000007c01a6010000ab0100000000000000007d067c06640064
+            0085027c026400640085026603190000000000000000007d067c067c0064
+            073c00000088126601640884087405000000000000000000007407000000
+            000000000000008912a6010000ab010000000000000000a6010000ab0100
+            000000000000004400a6000000ab00000000000000000064091900000000
+            00000000008a14881288146602640a840874050000000000000000000074
+            07000000000000000000008912891419000000000000000000640b190000
+            00000000000000a6010000ab010000000000000000a6010000ab01000000
+            00000000004400a6000000ab000000000000000000640919000000000000
+            0000007d07881288146602640c8408740500000000000000000000740700
+            0000000000000000008912891419000000000000000000640b1900000000
+            0000000000a6010000ab010000000000000000a6010000ab010000000000
+            0000004400a6000000ab0000000000000000006409190000000000000000
+            007d08881288146602640d84087405000000000000000000007407000000
+            000000000000008912891419000000000000000000640b19000000000000
+            000000a6010000ab010000000000000000a6010000ab0100000000000000
+            004400a6000000ab0000000000000000006409190000000000000000007d
+            09881288146602640e840874050000000000000000000074070000000000
+            00000000008912891419000000000000000000640b190000000000000000
+            00a6010000ab010000000000000000a6010000ab01000000000000000044
+            00a6000000ab0000000000000000006409190000000000000000007d0a89
+            12891419000000000000000000640b190000000000000000007c07190000
+            00000000000000640f190000000000000000007d0b891289141900000000
+            0000000000640b190000000000000000007c081900000000000000000064
+            0f190000000000000000006409190000000000000000007d0c8912891419
+            000000000000000000640b190000000000000000007c0919000000000000
+            000000640f190000000000000000006409190000000000000000007d0d89
+            12891419000000000000000000640b190000000000000000007c0a190000
+            00000000000000640f190000000000000000006409190000000000000000
+            007d0e881266016410840874050000000000000000000074070000000000
+            00000000008912a6010000ab010000000000000000a6010000ab01000000
+            00000000004400a6000000ab000000000000000000640919000000000000
+            0000008a1388128813660264118408740500000000000000000000740700
+            0000000000000000008912891319000000000000000000640b1900000000
+            0000000000a6010000ab010000000000000000a6010000ab010000000000
+            0000004400a6000000ab0000000000000000006409190000000000000000
+            007d0f8912891319000000000000000000640b190000000000000000007c
+            0f19000000000000000000640f190000000000000000007d107c0544005d
+            0d7d117c116412190000000000000000007c1164133c0000008c0e641489
+            127c067c017c037c047c057c0b7c107c0c7c0e7c0d670264159c0b5300
+                       0 MAKE_CELL               18 (GP)
+                       2 MAKE_CELL               19 (gp_analog_lbl_i)
+                       4 MAKE_CELL               20 (gp_point_lbl_i)
+         
+          83           6 RESUME                   0
+         
+          84           8 LOAD_FAST                0 (result)
+                      10 LOAD_CONST               1 ('GP')
+                      12 BINARY_SUBSCR
+                      22 STORE_DEREF             18 (GP)
+         
+          85          24 LOAD_FAST                0 (result)
+                      26 LOAD_CONST               2 ('Point')
+                      28 BINARY_SUBSCR
+                      38 STORE_FAST               1 (Point)
+         
+          86          40 LOAD_FAST                0 (result)
+                      42 LOAD_CONST               3 ('Real_marker_index')
+                      44 BINARY_SUBSCR
+                      54 STORE_FAST               2 (Real_marker_index)
+         
+          87          56 LOAD_FAST                0 (result)
+                      58 LOAD_CONST               4 ('Analog')
+                      60 BINARY_SUBSCR
+                      70 STORE_FAST               3 (Analog)
+         
+          88          72 LOAD_FAST                0 (result)
+                      74 LOAD_CONST               5 ('Header')
+                      76 BINARY_SUBSCR
+                      86 STORE_FAST               4 (Header)
+         
+          89          88 LOAD_FAST                0 (result)
+                      90 LOAD_CONST               6 ('Forceplate_list')
+                      92 BINARY_SUBSCR
+                     102 STORE_FAST               5 (Forceplates)
+         
+          90         104 LOAD_GLOBAL              1 (NULL + np)
+                     116 LOAD_ATTR                1 (array)
+                     126 LOAD_FAST                1 (Point)
+                     128 PRECALL                  1
+                     132 CALL                     1
+                     142 STORE_FAST               6 (Real_Markers)
+         
+          91         144 LOAD_FAST                6 (Real_Markers)
+                     146 LOAD_CONST               0 (None)
+                     148 LOAD_CONST               0 (None)
+                     150 BUILD_SLICE              2
+                     152 LOAD_FAST                2 (Real_marker_index)
+                     154 LOAD_CONST               0 (None)
+                     156 LOAD_CONST               0 (None)
+                     158 BUILD_SLICE              2
+                     160 BUILD_TUPLE              3
+                     162 BINARY_SUBSCR
+                     172 STORE_FAST               6 (Real_Markers)
+         
+          92         174 LOAD_FAST                6 (Real_Markers)
+                     176 LOAD_FAST                0 (result)
+                     178 LOAD_CONST               7 ('Markers')
+                     180 STORE_SUBSCR
+         
+          95         184 LOAD_CLOSURE            18 (GP)
+                     186 BUILD_TUPLE              1
+                     188 LOAD_CONST               8 (<code object <listcomp>, file "\Python311\Lib\site-packages\pyc3dtools\pyc3dtools.py", line 95>)
+                     190 MAKE_FUNCTION            8 (closure)
+         
+          96         192 LOAD_GLOBAL              5 (NULL + range)
+                     204 LOAD_GLOBAL              7 (NULL + len)
+                     216 LOAD_DEREF              18 (GP)
+                     218 PRECALL                  1
+                     222 CALL                     1
+                     232 PRECALL                  1
+                     236 CALL                     1
+         
+          95         246 GET_ITER
+                     248 PRECALL                  0
+                     252 CALL                     0
+         
+          98         262 LOAD_CONST               9 (0)
+         
+          95         264 BINARY_SUBSCR
+                     274 STORE_DEREF             20 (gp_point_lbl_i)
+         
+          99         276 LOAD_CLOSURE            18 (GP)
+                     278 LOAD_CLOSURE            20 (gp_point_lbl_i)
+                     280 BUILD_TUPLE              2
+                     282 LOAD_CONST              10 (<code object <listcomp>, file "\Python311\Lib\site-packages\pyc3dtools\pyc3dtools.py", line 99>)
+                     284 MAKE_FUNCTION            8 (closure)
+         
+         100         286 LOAD_GLOBAL              5 (NULL + range)
+                     298 LOAD_GLOBAL              7 (NULL + len)
+                     310 LOAD_DEREF              18 (GP)
+                     312 LOAD_DEREF              20 (gp_point_lbl_i)
+                     314 BINARY_SUBSCR
+                     324 LOAD_CONST              11 ('List_Parameters')
+                     326 BINARY_SUBSCR
+                     336 PRECALL                  1
+                     340 CALL                     1
+                     350 PRECALL                  1
+                     354 CALL                     1
+         
+          99         364 GET_ITER
+                     366 PRECALL                  0
+                     370 CALL                     0
+         
+         102         380 LOAD_CONST               9 (0)
+         
+          99         382 BINARY_SUBSCR
+                     392 STORE_FAST               7 (gp_point_lbl_ii)
+         
+         103         394 LOAD_CLOSURE            18 (GP)
+                     396 LOAD_CLOSURE            20 (gp_point_lbl_i)
+                     398 BUILD_TUPLE              2
+                     400 LOAD_CONST              12 (<code object <listcomp>, file "\Python311\Lib\site-packages\pyc3dtools\pyc3dtools.py", line 103>)
+                     402 MAKE_FUNCTION            8 (closure)
+         
+         104         404 LOAD_GLOBAL              5 (NULL + range)
+                     416 LOAD_GLOBAL              7 (NULL + len)
+                     428 LOAD_DEREF              18 (GP)
+                     430 LOAD_DEREF              20 (gp_point_lbl_i)
+                     432 BINARY_SUBSCR
+                     442 LOAD_CONST              11 ('List_Parameters')
+                     444 BINARY_SUBSCR
+                     454 PRECALL                  1
+                     458 CALL                     1
+                     468 PRECALL                  1
+                     472 CALL                     1
+         
+         103         482 GET_ITER
+                     484 PRECALL                  0
+                     488 CALL                     0
+         
+         106         498 LOAD_CONST               9 (0)
+         
+         103         500 BINARY_SUBSCR
+                     510 STORE_FAST               8 (gp_point_unit_i)
+         
+         107         512 LOAD_CLOSURE            18 (GP)
+                     514 LOAD_CLOSURE            20 (gp_point_lbl_i)
+                     516 BUILD_TUPLE              2
+                     518 LOAD_CONST              13 (<code object <listcomp>, file "\Python311\Lib\site-packages\pyc3dtools\pyc3dtools.py", line 107>)
+                     520 MAKE_FUNCTION            8 (closure)
+         
+         108         522 LOAD_GLOBAL              5 (NULL + range)
+                     534 LOAD_GLOBAL              7 (NULL + len)
+                     546 LOAD_DEREF              18 (GP)
+                     548 LOAD_DEREF              20 (gp_point_lbl_i)
+                     550 BINARY_SUBSCR
+                     560 LOAD_CONST              11 ('List_Parameters')
+                     562 BINARY_SUBSCR
+                     572 PRECALL                  1
+                     576 CALL                     1
+                     586 PRECALL                  1
+                     590 CALL                     1
+         
+         107         600 GET_ITER
+                     602 PRECALL                  0
+                     606 CALL                     0
+         
+         110         616 LOAD_CONST               9 (0)
+         
+         107         618 BINARY_SUBSCR
+                     628 STORE_FAST               9 (gp_point_Yscreen_i)
+         
+         111         630 LOAD_CLOSURE            18 (GP)
+                     632 LOAD_CLOSURE            20 (gp_point_lbl_i)
+                     634 BUILD_TUPLE              2
+                     636 LOAD_CONST              14 (<code object <listcomp>, file "\Python311\Lib\site-packages\pyc3dtools\pyc3dtools.py", line 111>)
+                     638 MAKE_FUNCTION            8 (closure)
+         
+         112         640 LOAD_GLOBAL              5 (NULL + range)
+                     652 LOAD_GLOBAL              7 (NULL + len)
+                     664 LOAD_DEREF              18 (GP)
+                     666 LOAD_DEREF              20 (gp_point_lbl_i)
+                     668 BINARY_SUBSCR
+                     678 LOAD_CONST              11 ('List_Parameters')
+                     680 BINARY_SUBSCR
+                     690 PRECALL                  1
+                     694 CALL                     1
+                     704 PRECALL                  1
+                     708 CALL                     1
+         
+         111         718 GET_ITER
+                     720 PRECALL                  0
+                     724 CALL                     0
+         
+         114         734 LOAD_CONST               9 (0)
+         
+         111         736 BINARY_SUBSCR
+                     746 STORE_FAST              10 (gp_point_Xscreen_i)
+         
+         115         748 LOAD_DEREF              18 (GP)
+                     750 LOAD_DEREF              20 (gp_point_lbl_i)
+                     752 BINARY_SUBSCR
+                     762 LOAD_CONST              11 ('List_Parameters')
+                     764 BINARY_SUBSCR
+                     774 LOAD_FAST                7 (gp_point_lbl_ii)
+                     776 BINARY_SUBSCR
+                     786 LOAD_CONST              15 ('Param_data')
+                     788 BINARY_SUBSCR
+                     798 STORE_FAST              11 (Markers_lbl)
+         
+         116         800 LOAD_DEREF              18 (GP)
+                     802 LOAD_DEREF              20 (gp_point_lbl_i)
+                     804 BINARY_SUBSCR
+                     814 LOAD_CONST              11 ('List_Parameters')
+                     816 BINARY_SUBSCR
+                     826 LOAD_FAST                8 (gp_point_unit_i)
+                     828 BINARY_SUBSCR
+                     838 LOAD_CONST              15 ('Param_data')
+                     840 BINARY_SUBSCR
+                     850 LOAD_CONST               9 (0)
+                     852 BINARY_SUBSCR
+                     862 STORE_FAST              12 (Markers_Units)
+         
+         117         864 LOAD_DEREF              18 (GP)
+                     866 LOAD_DEREF              20 (gp_point_lbl_i)
+                     868 BINARY_SUBSCR
+                     878 LOAD_CONST              11 ('List_Parameters')
+                     880 BINARY_SUBSCR
+                     890 LOAD_FAST                9 (gp_point_Yscreen_i)
+                     892 BINARY_SUBSCR
+                     902 LOAD_CONST              15 ('Param_data')
+                     904 BINARY_SUBSCR
+                     914 LOAD_CONST               9 (0)
+                     916 BINARY_SUBSCR
+                     926 STORE_FAST              13 (Markers_YSCREEN)
+         
+         118         928 LOAD_DEREF              18 (GP)
+                     930 LOAD_DEREF              20 (gp_point_lbl_i)
+                     932 BINARY_SUBSCR
+                     942 LOAD_CONST              11 ('List_Parameters')
+                     944 BINARY_SUBSCR
+                     954 LOAD_FAST               10 (gp_point_Xscreen_i)
+                     956 BINARY_SUBSCR
+                     966 LOAD_CONST              15 ('Param_data')
+                     968 BINARY_SUBSCR
+                     978 LOAD_CONST               9 (0)
+                     980 BINARY_SUBSCR
+                     990 STORE_FAST              14 (Markers_XSCREEN)
+         
+         121         992 LOAD_CLOSURE            18 (GP)
+                     994 BUILD_TUPLE              1
+                     996 LOAD_CONST              16 (<code object <listcomp>, file "\Python311\Lib\site-packages\pyc3dtools\pyc3dtools.py", line 121>)
+                     998 MAKE_FUNCTION            8 (closure)
+         
+         122        1000 LOAD_GLOBAL              5 (NULL + range)
+                    1012 LOAD_GLOBAL              7 (NULL + len)
+                    1024 LOAD_DEREF              18 (GP)
+                    1026 PRECALL                  1
+                    1030 CALL                     1
+                    1040 PRECALL                  1
+                    1044 CALL                     1
+         
+         121        1054 GET_ITER
+                    1056 PRECALL                  0
+                    1060 CALL                     0
+         
+         124        1070 LOAD_CONST               9 (0)
+         
+         121        1072 BINARY_SUBSCR
+                    1082 STORE_DEREF             19 (gp_analog_lbl_i)
+         
+         125        1084 LOAD_CLOSURE            18 (GP)
+                    1086 LOAD_CLOSURE            19 (gp_analog_lbl_i)
+                    1088 BUILD_TUPLE              2
+                    1090 LOAD_CONST              17 (<code object <listcomp>, file "\Python311\Lib\site-packages\pyc3dtools\pyc3dtools.py", line 125>)
+                    1092 MAKE_FUNCTION            8 (closure)
+         
+         126        1094 LOAD_GLOBAL              5 (NULL + range)
+                    1106 LOAD_GLOBAL              7 (NULL + len)
+                    1118 LOAD_DEREF              18 (GP)
+                    1120 LOAD_DEREF              19 (gp_analog_lbl_i)
+                    1122 BINARY_SUBSCR
+                    1132 LOAD_CONST              11 ('List_Parameters')
+                    1134 BINARY_SUBSCR
+                    1144 PRECALL                  1
+                    1148 CALL                     1
+                    1158 PRECALL                  1
+                    1162 CALL                     1
+         
+         125        1172 GET_ITER
+                    1174 PRECALL                  0
+                    1178 CALL                     0
+         
+         128        1188 LOAD_CONST               9 (0)
+         
+         125        1190 BINARY_SUBSCR
+                    1200 STORE_FAST              15 (gp_analog_lbl_ii)
+         
+         129        1202 LOAD_DEREF              18 (GP)
+                    1204 LOAD_DEREF              19 (gp_analog_lbl_i)
+                    1206 BINARY_SUBSCR
+                    1216 LOAD_CONST              11 ('List_Parameters')
+                    1218 BINARY_SUBSCR
+                    1228 LOAD_FAST               15 (gp_analog_lbl_ii)
+                    1230 BINARY_SUBSCR
+                    1240 LOAD_CONST              15 ('Param_data')
+                    1242 BINARY_SUBSCR
+                    1252 STORE_FAST              16 (Analog_lbl)
+         
+         133        1254 LOAD_FAST                5 (Forceplates)
+                    1256 GET_ITER
+                 >> 1258 FOR_ITER                13 (to 1286)
+                    1260 STORE_FAST              17 (f)
+         
+         134        1262 LOAD_FAST               17 (f)
+                    1264 LOAD_CONST              18 ('orgin')
+                    1266 BINARY_SUBSCR
+                    1276 LOAD_FAST               17 (f)
+                    1278 LOAD_CONST              19 ('Origin')
+                    1280 STORE_SUBSCR
+                    1284 JUMP_BACKWARD           14 (to 1258)
+         
+         137     >> 1286 LOAD_CONST              20 ('Success')
+         
+         138        1288 LOAD_DEREF              18 (GP)
+         
+         139        1290 LOAD_FAST                6 (Real_Markers)
+         
+         140        1292 LOAD_FAST                1 (Point)
+         
+         141        1294 LOAD_FAST                3 (Analog)
+         
+         142        1296 LOAD_FAST                4 (Header)
+         
+         143        1298 LOAD_FAST                5 (Forceplates)
+         
+         144        1300 LOAD_FAST               11 (Markers_lbl)
+         
+         145        1302 LOAD_FAST               16 (Analog_lbl)
+         
+         146        1304 LOAD_FAST               12 (Markers_Units)
+         
+         147        1306 LOAD_FAST               14 (Markers_XSCREEN)
+                    1308 LOAD_FAST               13 (Markers_YSCREEN)
+                    1310 BUILD_LIST               2
+         
+         136        1312 LOAD_CONST              21 (('Status', 'GP', 'Markers', 'Points', 'Analog', 'Header', 'ForcePlate', 'Markers Label', 'Analog Label', 'Units', 'Coordinate system'))
+                    1314 BUILD_CONST_KEY_MAP     11
+                    1316 RETURN_VALUE
+         consts
+            None
             'GP'
             'Point'
             'Real_marker_index'
             'Analog'
             'Header'
             'Forceplate_list'
             'Markers'
@@ -638,357 +1089,356 @@
                stacksize : 4
                flags     : 19
                code
                   0x9501970067007c005d167d0189027c0119000000000000000000640019
                   00000000000000000064016b0200000000af147c0191028c175300
                              0 COPY_FREE_VARS           1
                
-                48           2 RESUME                   0
+                95           2 RESUME                   0
                              4 BUILD_LIST               0
                              6 LOAD_FAST                0 (.0)
                        >>    8 FOR_ITER                22 (to 54)
                
-                49          10 STORE_FAST               1 (index)
+                96          10 STORE_FAST               1 (index)
                
-                50          12 LOAD_DEREF               2 (GP)
+                97          12 LOAD_DEREF               2 (GP)
                             14 LOAD_FAST                1 (index)
                             16 BINARY_SUBSCR
                             26 LOAD_CONST               0 ('Group_Name')
                             28 BINARY_SUBSCR
                             38 LOAD_CONST               1 ('POINT')
                             40 COMPARE_OP               2 (==)
                
-                48          46 POP_JUMP_BACKWARD_IF_FALSE    20 (to 8)
+                95          46 POP_JUMP_BACKWARD_IF_FALSE    20 (to 8)
                
-                49          48 LOAD_FAST                1 (index)
+                96          48 LOAD_FAST                1 (index)
                
-                48          50 LIST_APPEND              2
+                95          50 LIST_APPEND              2
                             52 JUMP_BACKWARD           23 (to 8)
                        >>   54 RETURN_VALUE
                consts
                   'Group_Name'
                   'POINT'
                names      ()
                varnames   ('.0', 'index')
                freevars   ('GP',)
                cellvars   ()
                filename   '\\Python311\\Lib\\site-packages\\pyc3dtools\\pyc3dtools.py'
                name       '<listcomp>'
-               firstlineno 48
+               firstlineno 95
                lnotab 0x0a01020122fe020102ff
             0
             code
                argcount  : 1
                nlocals   : 2
                stacksize : 4
                flags     : 19
                code
                   0x9502970067007c005d227d018902890319000000000000000000640019
                   0000000000000000007c0119000000000000000000640119000000000000
                   00000064026b0200000000af207c0191028c235300
                              0 COPY_FREE_VARS           2
                
-                52           2 RESUME                   0
+                99           2 RESUME                   0
                              4 BUILD_LIST               0
                              6 LOAD_FAST                0 (.0)
                        >>    8 FOR_ITER                34 (to 78)
                
-                53          10 STORE_FAST               1 (index)
+               100          10 STORE_FAST               1 (index)
                
-                54          12 LOAD_DEREF               2 (GP)
+               101          12 LOAD_DEREF               2 (GP)
                             14 LOAD_DEREF               3 (gp_point_lbl_i)
                             16 BINARY_SUBSCR
                             26 LOAD_CONST               0 ('List_Parameters')
                             28 BINARY_SUBSCR
                             38 LOAD_FAST                1 (index)
                             40 BINARY_SUBSCR
                             50 LOAD_CONST               1 ('Param_Name')
                             52 BINARY_SUBSCR
                             62 LOAD_CONST               2 ('LABELS')
                             64 COMPARE_OP               2 (==)
                
-                52          70 POP_JUMP_BACKWARD_IF_FALSE    32 (to 8)
+                99          70 POP_JUMP_BACKWARD_IF_FALSE    32 (to 8)
                
-                53          72 LOAD_FAST                1 (index)
+               100          72 LOAD_FAST                1 (index)
                
-                52          74 LIST_APPEND              2
+                99          74 LIST_APPEND              2
                             76 JUMP_BACKWARD           35 (to 8)
                        >>   78 RETURN_VALUE
                consts
                   'List_Parameters'
                   'Param_Name'
                   'LABELS'
                names      ()
                varnames   ('.0', 'index')
                freevars   ('GP', 'gp_point_lbl_i')
                cellvars   ()
                filename   '\\Python311\\Lib\\site-packages\\pyc3dtools\\pyc3dtools.py'
                name       '<listcomp>'
-               firstlineno 52
+               firstlineno 99
                lnotab 0x0a0102013afe020102ff
             'List_Parameters'
             code
                argcount  : 1
                nlocals   : 2
                stacksize : 4
                flags     : 19
                code
                   0x9502970067007c005d227d018902890319000000000000000000640019
                   0000000000000000007c0119000000000000000000640119000000000000
                   00000064026b0200000000af207c0191028c235300
                              0 COPY_FREE_VARS           2
                
-                56           2 RESUME                   0
+               103           2 RESUME                   0
                              4 BUILD_LIST               0
                              6 LOAD_FAST                0 (.0)
                        >>    8 FOR_ITER                34 (to 78)
                
-                57          10 STORE_FAST               1 (index)
+               104          10 STORE_FAST               1 (index)
                
-                58          12 LOAD_DEREF               2 (GP)
+               105          12 LOAD_DEREF               2 (GP)
                             14 LOAD_DEREF               3 (gp_point_lbl_i)
                             16 BINARY_SUBSCR
                             26 LOAD_CONST               0 ('List_Parameters')
                             28 BINARY_SUBSCR
                             38 LOAD_FAST                1 (index)
                             40 BINARY_SUBSCR
                             50 LOAD_CONST               1 ('Param_Name')
                             52 BINARY_SUBSCR
                             62 LOAD_CONST               2 ('UNITS')
                             64 COMPARE_OP               2 (==)
                
-                56          70 POP_JUMP_BACKWARD_IF_FALSE    32 (to 8)
+               103          70 POP_JUMP_BACKWARD_IF_FALSE    32 (to 8)
                
-                57          72 LOAD_FAST                1 (index)
+               104          72 LOAD_FAST                1 (index)
                
-                56          74 LIST_APPEND              2
+               103          74 LIST_APPEND              2
                             76 JUMP_BACKWARD           35 (to 8)
                        >>   78 RETURN_VALUE
                consts
                   'List_Parameters'
                   'Param_Name'
                   'UNITS'
                names      ()
                varnames   ('.0', 'index')
                freevars   ('GP', 'gp_point_lbl_i')
                cellvars   ()
                filename   '\\Python311\\Lib\\site-packages\\pyc3dtools\\pyc3dtools.py'
                name       '<listcomp>'
-               firstlineno 56
+               firstlineno 103
                lnotab 0x0a0102013afe020102ff
             code
                argcount  : 1
                nlocals   : 2
                stacksize : 4
                flags     : 19
                code
                   0x9502970067007c005d227d018902890319000000000000000000640019
                   0000000000000000007c0119000000000000000000640119000000000000
                   00000064026b0200000000af207c0191028c235300
                              0 COPY_FREE_VARS           2
                
-                60           2 RESUME                   0
+               107           2 RESUME                   0
                              4 BUILD_LIST               0
                              6 LOAD_FAST                0 (.0)
                        >>    8 FOR_ITER                34 (to 78)
                
-                61          10 STORE_FAST               1 (index)
+               108          10 STORE_FAST               1 (index)
                
-                62          12 LOAD_DEREF               2 (GP)
+               109          12 LOAD_DEREF               2 (GP)
                             14 LOAD_DEREF               3 (gp_point_lbl_i)
                             16 BINARY_SUBSCR
                             26 LOAD_CONST               0 ('List_Parameters')
                             28 BINARY_SUBSCR
                             38 LOAD_FAST                1 (index)
                             40 BINARY_SUBSCR
                             50 LOAD_CONST               1 ('Param_Name')
                             52 BINARY_SUBSCR
                             62 LOAD_CONST               2 ('Y_SCREEN')
                             64 COMPARE_OP               2 (==)
                
-                60          70 POP_JUMP_BACKWARD_IF_FALSE    32 (to 8)
+               107          70 POP_JUMP_BACKWARD_IF_FALSE    32 (to 8)
                
-                61          72 LOAD_FAST                1 (index)
+               108          72 LOAD_FAST                1 (index)
                
-                60          74 LIST_APPEND              2
+               107          74 LIST_APPEND              2
                             76 JUMP_BACKWARD           35 (to 8)
                        >>   78 RETURN_VALUE
                consts
                   'List_Parameters'
                   'Param_Name'
                   'Y_SCREEN'
                names      ()
                varnames   ('.0', 'index')
                freevars   ('GP', 'gp_point_lbl_i')
                cellvars   ()
                filename   '\\Python311\\Lib\\site-packages\\pyc3dtools\\pyc3dtools.py'
                name       '<listcomp>'
-               firstlineno 60
+               firstlineno 107
                lnotab 0x0a0102013afe020102ff
             code
                argcount  : 1
                nlocals   : 2
                stacksize : 4
                flags     : 19
                code
                   0x9502970067007c005d227d018902890319000000000000000000640019
                   0000000000000000007c0119000000000000000000640119000000000000
                   00000064026b0200000000af207c0191028c235300
                              0 COPY_FREE_VARS           2
                
-                64           2 RESUME                   0
+               111           2 RESUME                   0
                              4 BUILD_LIST               0
                              6 LOAD_FAST                0 (.0)
                        >>    8 FOR_ITER                34 (to 78)
                
-                65          10 STORE_FAST               1 (index)
+               112          10 STORE_FAST               1 (index)
                
-                66          12 LOAD_DEREF               2 (GP)
+               113          12 LOAD_DEREF               2 (GP)
                             14 LOAD_DEREF               3 (gp_point_lbl_i)
                             16 BINARY_SUBSCR
                             26 LOAD_CONST               0 ('List_Parameters')
                             28 BINARY_SUBSCR
                             38 LOAD_FAST                1 (index)
                             40 BINARY_SUBSCR
                             50 LOAD_CONST               1 ('Param_Name')
                             52 BINARY_SUBSCR
                             62 LOAD_CONST               2 ('X_SCREEN')
                             64 COMPARE_OP               2 (==)
                
-                64          70 POP_JUMP_BACKWARD_IF_FALSE    32 (to 8)
+               111          70 POP_JUMP_BACKWARD_IF_FALSE    32 (to 8)
                
-                65          72 LOAD_FAST                1 (index)
+               112          72 LOAD_FAST                1 (index)
                
-                64          74 LIST_APPEND              2
+               111          74 LIST_APPEND              2
                             76 JUMP_BACKWARD           35 (to 8)
                        >>   78 RETURN_VALUE
                consts
                   'List_Parameters'
                   'Param_Name'
                   'X_SCREEN'
                names      ()
                varnames   ('.0', 'index')
                freevars   ('GP', 'gp_point_lbl_i')
                cellvars   ()
                filename   '\\Python311\\Lib\\site-packages\\pyc3dtools\\pyc3dtools.py'
                name       '<listcomp>'
-               firstlineno 64
+               firstlineno 111
                lnotab 0x0a0102013afe020102ff
             'Param_data'
             code
                argcount  : 1
                nlocals   : 2
                stacksize : 4
                flags     : 19
                code
                   0x9501970067007c005d167d0189027c0119000000000000000000640019
                   00000000000000000064016b0200000000af147c0191028c175300
                              0 COPY_FREE_VARS           1
                
-                74           2 RESUME                   0
+               121           2 RESUME                   0
                              4 BUILD_LIST               0
                              6 LOAD_FAST                0 (.0)
                        >>    8 FOR_ITER                22 (to 54)
                
-                75          10 STORE_FAST               1 (index)
+               122          10 STORE_FAST               1 (index)
                
-                76          12 LOAD_DEREF               2 (GP)
+               123          12 LOAD_DEREF               2 (GP)
                             14 LOAD_FAST                1 (index)
                             16 BINARY_SUBSCR
                             26 LOAD_CONST               0 ('Group_Name')
                             28 BINARY_SUBSCR
                             38 LOAD_CONST               1 ('ANALOG')
                             40 COMPARE_OP               2 (==)
                
-                74          46 POP_JUMP_BACKWARD_IF_FALSE    20 (to 8)
+               121          46 POP_JUMP_BACKWARD_IF_FALSE    20 (to 8)
                
-                75          48 LOAD_FAST                1 (index)
+               122          48 LOAD_FAST                1 (index)
                
-                74          50 LIST_APPEND              2
+               121          50 LIST_APPEND              2
                             52 JUMP_BACKWARD           23 (to 8)
                        >>   54 RETURN_VALUE
                consts
                   'Group_Name'
                   'ANALOG'
                names      ()
                varnames   ('.0', 'index')
                freevars   ('GP',)
                cellvars   ()
                filename   '\\Python311\\Lib\\site-packages\\pyc3dtools\\pyc3dtools.py'
                name       '<listcomp>'
-               firstlineno 74
+               firstlineno 121
                lnotab 0x0a01020122fe020102ff
             code
                argcount  : 1
                nlocals   : 2
                stacksize : 4
                flags     : 19
                code
                   0x9502970067007c005d227d018902890319000000000000000000640019
                   0000000000000000007c0119000000000000000000640119000000000000
                   00000064026b0200000000af207c0191028c235300
                              0 COPY_FREE_VARS           2
                
-                78           2 RESUME                   0
+               125           2 RESUME                   0
                              4 BUILD_LIST               0
                              6 LOAD_FAST                0 (.0)
                        >>    8 FOR_ITER                34 (to 78)
                
-                79          10 STORE_FAST               1 (index)
+               126          10 STORE_FAST               1 (index)
                
-                80          12 LOAD_DEREF               2 (GP)
+               127          12 LOAD_DEREF               2 (GP)
                             14 LOAD_DEREF               3 (gp_analog_lbl_i)
                             16 BINARY_SUBSCR
                             26 LOAD_CONST               0 ('List_Parameters')
                             28 BINARY_SUBSCR
                             38 LOAD_FAST                1 (index)
                             40 BINARY_SUBSCR
                             50 LOAD_CONST               1 ('Param_Name')
                             52 BINARY_SUBSCR
                             62 LOAD_CONST               2 ('LABELS')
                             64 COMPARE_OP               2 (==)
                
-                78          70 POP_JUMP_BACKWARD_IF_FALSE    32 (to 8)
+               125          70 POP_JUMP_BACKWARD_IF_FALSE    32 (to 8)
                
-                79          72 LOAD_FAST                1 (index)
+               126          72 LOAD_FAST                1 (index)
                
-                78          74 LIST_APPEND              2
+               125          74 LIST_APPEND              2
                             76 JUMP_BACKWARD           35 (to 8)
                        >>   78 RETURN_VALUE
                consts
                   'List_Parameters'
                   'Param_Name'
                   'LABELS'
                names      ()
                varnames   ('.0', 'index')
                freevars   ('GP', 'gp_analog_lbl_i')
                cellvars   ()
                filename   '\\Python311\\Lib\\site-packages\\pyc3dtools\\pyc3dtools.py'
                name       '<listcomp>'
-               firstlineno 78
+               firstlineno 125
                lnotab 0x0a0102013afe020102ff
             'orgin'
             'Origin'
-            ('GP', 'Markers', 'Points', 'Analog', 'Header', 'ForcePlate', 'Markers Label', 'Analog Label', 'Units', 'Coordinate system')
-            'Failed'
-         names      ('os', 'stat', 'st_size', 'open', 'tqdm', 'CallbackIOWrapper', 'update', 'requests', 'post', 'API_URL', 'json', 'loads', 'text', 'np', 'array', 'range', 'len', 'KeyError')
-         varnames   ('Token', 'file_path', 'data', 'file_size', 'f', 't', 'wrapped_file', 'resp', 'result', 'Point', 'Real_marker_index', 'Analog', 'Header', 'Forceplates', 'Real_Markers', 'gp_point_lbl_ii', 'gp_point_unit_i', 'gp_point_Yscreen_i', 'gp_point_Xscreen_i', 'Markers_lbl', 'Markers_Units', 'Markers_YSCREEN', 'Markers_XSCREEN', 'gp_analog_lbl_ii', 'Analog_lbl')
+            'Success'
+            ('Status', 'GP', 'Markers', 'Points', 'Analog', 'Header', 'ForcePlate', 'Markers Label', 'Analog Label', 'Units', 'Coordinate system')
+         names      ('np', 'array', 'range', 'len')
+         varnames   ('result', 'Point', 'Real_marker_index', 'Analog', 'Header', 'Forceplates', 'Real_Markers', 'gp_point_lbl_ii', 'gp_point_unit_i', 'gp_point_Yscreen_i', 'gp_point_Xscreen_i', 'Markers_lbl', 'Markers_Units', 'Markers_YSCREEN', 'Markers_XSCREEN', 'gp_analog_lbl_ii', 'Analog_lbl', 'f')
          freevars   ()
          cellvars   ('GP', 'gp_analog_lbl_i', 'gp_point_lbl_i')
          filename   '\\Python311\\Lib\\site-packages\\pyc3dtools\\pyc3dtools.py'
-         name       'readC3D'
-         firstlineno 11
+         name       'GenerateOutput'
+         firstlineno 83
          lnotab
-            0x080208033201220128012c013cfe2eff2e0632020201080210ff040510
-            011001100110011001100128011e010a040404080136ff100302fd0c040a
-            014eff100302fd0c040a014eff100302fd0c040a014eff100302fd0c040a
-            014eff100302fd0c043401400140014003080136ff100302fd0c040a014e
-            ff100302fd0c043405080118030201020102010201020102010201020102
-            0106f6080c120204ff08ff
-   names      ('requests', 'json', 'numpy', 'np', 'os', 'tqdm', 'tqdm.utils', 'CallbackIOWrapper', 'API_URL', 'readC3D')
+            0x080110011001100110011001100128011e010a03080136ff100302fd0c
+            040a014eff100302fd0c040a014eff100302fd0c040a014eff100302fd0c
+            040a014eff100302fd0c043401400140014003080136ff100302fd0c040a
+            014eff100302fd0c04340408011803020102010201020102010201020102
+            010201020106f5
+   names      ('requests', 'json', 'numpy', 'np', 'os', 'tqdm', 'tqdm.utils', 'CallbackIOWrapper', 'readC3D', 'getTRCMot', 'GenerateOutput')
    varnames   ()
    freevars   ()
    cellvars   ()
    filename   '\\Python311\\Lib\\site-packages\\pyc3dtools\\pyc3dtools.py'
    name       '<module>'
    firstlineno 1
-   lnotab 0x00ff02011001080108010c010c030403
+   lnotab 0x00ff02011001080108010c010c03061e062d
```

## Python311/Lib/site-packages/pyc3dtools/__pycache__/__init__.cpython-311.pyc

### Python bytecode

```diff
@@ -1,31 +1,41 @@
 magic:    0xa70d0d0a
-moddate:  0xba744e64 (Sun Apr 30 14:01:30 2023 UTC)
-files sz: 41
+moddate:  0x1e0b5964 (Mon May  8 14:45:50 2023 UTC)
+files sz: 88
 code
    argcount  : 0
    nlocals   : 0
    stacksize : 2
    flags     : 0
-   code 0x9700640064016c006d015a01010064025300
+   code
+      0x9700640064016c006d015a010100640064026c006d025a020100640353
+      00
      0           0 RESUME                   0
    
      1           2 LOAD_CONST               0 (0)
                  4 LOAD_CONST               1 (('readC3D',))
                  6 IMPORT_NAME              0 (pyc3dtools.pyc3dtools)
                  8 IMPORT_FROM              1 (readC3D)
                 10 STORE_NAME               1 (readC3D)
                 12 POP_TOP
-                14 LOAD_CONST               2 (None)
-                16 RETURN_VALUE
+   
+     2          14 LOAD_CONST               0 (0)
+                16 LOAD_CONST               2 (('getTRCMot',))
+                18 IMPORT_NAME              0 (pyc3dtools.pyc3dtools)
+                20 IMPORT_FROM              2 (getTRCMot)
+                22 STORE_NAME               2 (getTRCMot)
+                24 POP_TOP
+                26 LOAD_CONST               3 (None)
+                28 RETURN_VALUE
    consts
       0
       ('readC3D',)
+      ('getTRCMot',)
       None
-   names      ('pyc3dtools.pyc3dtools', 'readC3D')
+   names      ('pyc3dtools.pyc3dtools', 'readC3D', 'getTRCMot')
    varnames   ()
    freevars   ()
    cellvars   ()
    filename   '\\Python311\\Lib\\site-packages\\pyc3dtools\\__init__.py'
    name       '<module>'
    firstlineno 1
-   lnotab 0x00ff0201
+   lnotab 0x00ff02010c01
```

